src/csa3_16.v
module csa3_16(
  input  [15:0] x,
  input  [15:0] y,
  input  [15:0] z,
  output [15:0] sum,
  output [15:0] carry_sh
);
  assign sum = x ^ y ^ z;
  assign carry_sh = ((x & y) | (y & z) | (x & z)) << 1;
endmodule

src/multiplier_wallace.v
// 8x8 Wallace-like multiplier using carry-save adder (CSA) tree
module multiplier_wallace(
    input  [7:0] a,
    input  [7:0] b,
    output [15:0] product
);

  // 16-bit shifted partial products
  wire [15:0] pp_shift [7:0];
  genvar k;
  generate
    for (k = 0; k < 8; k = k + 1) begin : gen_pp_shifts
      // extend a into 16 bits then shift by k
      assign pp_shift[k] = b[k] ? ({8'b0, a} << k) : 16'b0;
    end
  endgenerate

  // Stage 1: reduce groups of three partial products
  wire [15:0] s1, c1, s2, c2, s3, c3;
  csa3_16 u1 (pp_shift[0], pp_shift[1], pp_shift[2], s1, c1);
  csa3_16 u2 (pp_shift[3], pp_shift[4], pp_shift[5], s2, c2);
  csa3_16 u3 (pp_shift[6], pp_shift[7], 16'b0,          s3, c3);

  // Stage 2: reduce the stage-1 sums and the stage-1 carries
  wire [15:0] s4, c4, s5, c5;
  csa3_16 u4 (s1, s2, s3, s4, c4);
  csa3_16 u5 (c1, c2, c3, s5, c5); // c1/c2/c3 already include their left-shift

  // Stage 3: reduce the two resulting sums
  wire [15:0] s6, c6;
  csa3_16 u6 (s4, s5, 16'b0, s6, c6);

  // Final: add remaining operands (s6 + c4 + c5 + c6). All carries produced by CSA are left-shifted.
  assign product = s6 + c4 + c5 + c6;

endmodule

// 3:2 carry-save adder for 16-bit vectors.
// sum = x ^ y ^ z
// carry_sh = ((x&y) | (y&z) | (x&z)) << 1  (carry bits shifted to next weight)

src/mac_unit.v
`timescale 1ns/1ps
module mac_unit (
    input  [7:0]  a,
    input  [7:0]  b,
    input  [15:0] acc,
    output [15:0] mac_out
);

    wire [15:0] product;

    // Use your Wallace multiplier
    multiplier_wallace mul (
        .a(a),
        .b(b),
        .product(product)
    );

    assign mac_out = product + acc;

endmodule

// This is intentionally simple — because for now we focus on functional comparison.
// Later we will add CLA adder + pipelining enhancements.

tb/tb_mac.v
`timescale 1ns/1ps

module tb_mac;

    reg  [7:0]  a, b;
    reg  [15:0] acc;
    wire [15:0] mac_out;

    integer i;

    // Instantiate MAC Unit
    mac_unit DUT (
        .a(a),
        .b(b),
        .acc(acc),
        .mac_out(mac_out)
    );

    initial begin
        $dumpfile("waves/mac_unit.vcd");
        $dumpvars(0, tb_mac);

        // Directed Tests
        a = 8'd5; b = 8'd10; acc = 16'd20; #10;
        a = 8'd15; b = 8'd3; acc = 16'd7;   #10;
        a = 8'd255; b = 8'd1; acc = 16'd0;  #10;
        a = 8'd100; b = 8'd2; acc = 16'd50; #10;

        // Random Tests
        for (i = 0; i < 2000; i = i + 1) begin
            a   = $random % 256;
            b   = $random % 256;
            acc = $random % 65536;
            #1;
            if (mac_out !== (a * b + acc)) begin
                $display("ERROR: a=%0d b=%0d acc=%0d mac_out=%0d expected=%0d",
                         a, b, acc, mac_out, (a*b + acc));
                $finish;
            end
            #4;
        end

        $display("All MAC tests passed!");
        #100 $finish;
    end

endmodule

waves/mac_unit.vcd
$date
	Mon Nov 17 10:18:09 2025
$end
$version
	Icarus Verilog
$end
$timescale
	1ps
$end
$scope module tb_mac $end
$var wire 16 ! mac_out [15:0] $end
$var reg 8 " a [7:0] $end
$var reg 16 # acc [15:0] $end
$var reg 8 $ b [7:0] $end
$var integer 32 % i [31:0] $end
$scope module DUT $end
$var wire 8 & a [7:0] $end
$var wire 16 ' acc [15:0] $end
$var wire 8 ( b [7:0] $end
$var wire 16 ) product [15:0] $end
$var wire 16 * mac_out [15:0] $end
$scope module mul $end
$var wire 8 + a [7:0] $end
$var wire 8 , b [7:0] $end
$var wire 16 - s6 [15:0] $end
$var wire 16 . s5 [15:0] $end
$var wire 16 / s4 [15:0] $end
$var wire 16 0 s3 [15:0] $end
$var wire 16 1 s2 [15:0] $end
$var wire 16 2 s1 [15:0] $end
$var wire 16 3 product [15:0] $end
$var wire 16 4 c6 [15:0] $end
$var wire 16 5 c5 [15:0] $end
$var wire 16 6 c4 [15:0] $end
$var wire 16 7 c3 [15:0] $end
$var wire 16 8 c2 [15:0] $end
$var wire 16 9 c1 [15:0] $end
$scope begin gen_pp_shifts[0] $end
$var parameter 2 : k $end
$upscope $end
$scope begin gen_pp_shifts[1] $end
$var parameter 2 ; k $end
$upscope $end
$scope begin gen_pp_shifts[2] $end
$var parameter 3 < k $end
$upscope $end
$scope begin gen_pp_shifts[3] $end
$var parameter 3 = k $end
$upscope $end
$scope begin gen_pp_shifts[4] $end
$var parameter 4 > k $end
$upscope $end
$scope begin gen_pp_shifts[5] $end
$var parameter 4 ? k $end
$upscope $end
$scope begin gen_pp_shifts[6] $end
$var parameter 4 @ k $end
$upscope $end
$scope begin gen_pp_shifts[7] $end
$var parameter 4 A k $end
$upscope $end
$scope module u1 $end
$var wire 16 B sum [15:0] $end
$var wire 16 C x [15:0] $end
$var wire 16 D y [15:0] $end
$var wire 16 E z [15:0] $end
$var wire 16 F carry_sh [15:0] $end
$upscope $end
$scope module u2 $end
$var wire 16 G sum [15:0] $end
$var wire 16 H x [15:0] $end
$var wire 16 I y [15:0] $end
$var wire 16 J z [15:0] $end
$var wire 16 K carry_sh [15:0] $end
$upscope $end
$scope module u3 $end
$var wire 16 L sum [15:0] $end
$var wire 16 M x [15:0] $end
$var wire 16 N y [15:0] $end
$var wire 16 O z [15:0] $end
$var wire 16 P carry_sh [15:0] $end
$upscope $end
$scope module u4 $end
$var wire 16 Q sum [15:0] $end
$var wire 16 R x [15:0] $end
$var wire 16 S y [15:0] $end
$var wire 16 T z [15:0] $end
$var wire 16 U carry_sh [15:0] $end
$upscope $end
$scope module u5 $end
$var wire 16 V sum [15:0] $end
$var wire 16 W x [15:0] $end
$var wire 16 X y [15:0] $end
$var wire 16 Y z [15:0] $end
$var wire 16 Z carry_sh [15:0] $end
$upscope $end
$scope module u6 $end
$var wire 16 [ sum [15:0] $end
$var wire 16 \ x [15:0] $end
$var wire 16 ] y [15:0] $end
$var wire 16 ^ z [15:0] $end
$var wire 16 _ carry_sh [15:0] $end
$upscope $end
$upscope $end
$upscope $end
$upscope $end
$enddefinitions $end
$comment Show the parameter values. $end
$dumpall
b111 A
b110 @
b101 ?
b100 >
b11 =
b10 <
b1 ;
b0 :
$end
#0
$dumpvars
b0 _
b0 ^
b0 ]
b100010 \
b100010 [
b0 Z
b0 Y
b0 X
b0 W
b0 V
b10000 U
b0 T
b101000 S
b1010 R
b100010 Q
b0 P
b0 O
b0 N
b0 M
b0 L
b0 K
b0 J
b0 I
b101000 H
b101000 G
b0 F
b0 E
b1010 D
b0 C
b1010 B
b0 9
b0 8
b0 7
b10000 6
b0 5
b0 4
b110010 3
b1010 2
b101000 1
b0 0
b100010 /
b0 .
b100010 -
b1010 ,
b101 +
b1000110 *
b110010 )
b1010 (
b10100 '
b101 &
bx %
b1010 $
b10100 #
b101 "
b1000110 !
$end
#10000
b100000 4
b100000 _
b11100 .
b11100 V
b11100 ]
b1101 -
b1101 [
b101101 )
b101101 3
b0 6
b0 U
b11100 9
b11100 F
b11100 W
b10001 /
b10001 Q
b10001 \
b10001 2
b10001 B
b10001 R
b0 1
b0 G
b0 S
b1111 C
b11110 D
b0 H
b110100 !
b110100 *
b111 #
b111 '
b11 $
b11 (
b11 ,
b1111 "
b1111 &
b1111 +
#20000
b0 4
b0 _
b11111111 )
b11111111 3
b11111111 -
b11111111 [
b0 .
b0 V
b0 ]
b11111111 /
b11111111 Q
b11111111 \
b0 9
b0 F
b0 W
b11111111 2
b11111111 B
b11111111 R
b0 D
b11111111 C
b11111111 !
b11111111 *
b0 #
b0 '
b1 $
b1 (
b1 ,
b11111111 "
b11111111 &
b11111111 +
#30000
b11001000 )
b11001000 3
b11001000 -
b11001000 [
b11001000 /
b11001000 Q
b11001000 \
b11001000 2
b11001000 B
b11001000 R
b11001000 D
b0 C
b11111010 !
b11111010 *
b110010 #
b110010 '
b10 $
b10 (
b10 ,
b1100100 "
b1100100 &
b1100100 +
#40000
b1001000100100 )
b1001000100100 3
b1001000100100 -
b1001000100100 [
b1001000100100 /
b1001000100100 Q
b1001000100100 \
b1001000000000 0
b1001000000000 L
b1001000000000 T
b100100 2
b100100 B
b100100 R
b100100 C
b1001000000000 N
b0 D
b1110100000101101 !
b1110100000101101 *
b1101011000001001 #
b1101011000001001 '
b10000001 $
b10000001 (
b10000001 ,
b100100 "
b100100 &
b100100 +
b0 %
#45000
b1000010000 6
b1000010000 U
b10100000111 )
b10100000111 3
b1011110111 -
b1011110111 [
b1011110111 /
b1011110111 Q
b1011110111 \
b1100011000 1
b1100011000 G
b1100011000 S
b0 0
b0 L
b0 T
b111101111 2
b111101111 B
b111101111 R
b110001100 E
b1100011000 H
b0 N
b1100011 C
b1001111010010100 !
b1001111010010100 *
b1001100110001101 #
b1001100110001101 '
b1101 $
b1101 (
b1101 ,
b1100011 "
b1100011 &
b1100011 +
b1 %
#50000
b11010011010 -
b11010011010 [
b11100011010 )
b11100011010 3
b10000000 6
b10000000 U
b11010011010 /
b11010011010 Q
b11010011010 \
b11001010000 1
b11001010000 G
b11001010000 S
b11001010 2
b11001010 B
b11001010 R
b11001010 D
b11001010000 I
b0 E
b0 H
b0 C
b1110101000011011 !
b1110101000011011 *
b1110001100000001 #
b1110001100000001 '
b10010 $
b10010 (
b10010 ,
b1100101 "
b1100101 &
b1100101 +
b10 %
#55000
b100100000 .
b100100000 V
b100100000 ]
b1011000000 6
b1011000000 U
b10111111110 )
b10111111110 3
b1100111110 -
b1100111110 [
b100000 9
b100000 F
b100000 W
b100000000 8
b100000000 K
b100000000 X
b1000011110 /
b1000011110 Q
b1000011110 \
b1101000000 0
b1101000000 L
b1101000000 T
b101110 2
b101110 B
b101110 R
b101110000 1
b101110000 G
b101110000 S
b110100 E
b110100000 J
b1101000000 M
b11010 D
b11010000 I
b1101001100111011 !
b1101001100111011 *
b1100110100111101 #
b1100110100111101 '
b1110110 $
b1110110 (
b1110110 ,
b1101 "
b1101 &
b1101 +
b11 %
#60000
b0 4
b0 _
b0 .
b0 V
b0 ]
b111001001011100 -
b111001001011100 [
b1000000110011100 )
b1000000110011100 3
b111101000000 6
b111101000000 U
b0 9
b0 F
b0 W
b0 8
b0 K
b0 X
b111001001011100 /
b111001001011100 Q
b111001001011100 \
b111011010000000 0
b111011010000000 L
b111011010000000 T
b1110110100 2
b1110110100 B
b1110110100 R
b11101101000 1
b11101101000 G
b11101101000 S
b11101101000 H
b111011010000000 N
b0 D
b1110110100 E
b0 I
b0 J
b0 M
b110101110010101 !
b110101110010101 *
b1110100111111001 #
b1110100111111001 '
b10001100 $
b10001100 (
b10001100 ,
b11101101 "
b11101101 &
b11101101 +
b100 %
#65000
b1000000000000000 4
b1000000000000000 _
b1001101011110 -
b1001101011110 [
b100001000000000 .
b100001000000000 V
b100001000000000 ]
b1001100001011110 )
b1001100001011110 3
b10100000000 6
b10100000000 U
b100001000000000 7
b100001000000000 P
b100001000000000 Y
b101000101011110 /
b101000101011110 Q
b101000101011110 \
b0 1
b0 G
b0 S
b101001010000000 0
b101001010000000 L
b101001010000000 T
b1111011110 2
b1111011110 B
b1111011110 R
b11000110 C
b11000110000000 M
b1100011000 E
b0 H
b110001100000000 N
b110101100001000 !
b110101100001000 *
b1101001010101010 #
b1101001010101010 '
b11000101 $
b11000101 (
b11000101 ,
b11000110 "
b11000110 &
b11000110 +
b101 %
#70000
b1001000010000 4
b1001000010000 _
b11001010000011 -
b11001010000011 [
b1100000000000 8
b1100000000000 K
b1100000000000 X
b1101110001000 .
b1101110001000 V
b1101110001000 ]
b110101001110011 )
b110101001110011 3
b10010111100000 6
b10010111100000 U
b0 7
b0 P
b0 Y
b10100100001011 /
b10100100001011 Q
b10100100001011 \
b1110001000 9
b1110001000 F
b1110001000 W
b11100101000000 0
b11100101000000 L
b11100101000000 T
b1001011110000 1
b1001011110000 G
b1001011110000 S
b1010111011 2
b1010111011 B
b1010111011 R
b111001010 D
b111001010000 I
b1110010100000 J
b1110010100 E
b11100101000000 M
b0 N
b11100101 C
b100000010000101 !
b100000010000101 *
b1101011000010010 #
b1101011000010010 '
b1110111 $
b1110111 (
b1110111 ,
b11100101 "
b11100101 &
b11100101 +
b110 %
#75000
b1000000000 5
b1000000000 Z
b100010000000 4
b100010000000 _
b1000100000 6
b1000100000 U
b1000011100101110 )
b1000011100101110 3
b111101010001110 -
b111101010001110 [
b11011000000 .
b11011000000 V
b11011000000 ]
b111000000 8
b111000000 K
b111000000 X
b11100000000 7
b11100000000 P
b11100000000 Y
b111110001001110 /
b111110001001110 Q
b111110001001110 \
b0 9
b0 F
b0 W
b110010001000000 0
b110010001000000 L
b110010001000000 T
b100011110 2
b100011110 B
b100011110 R
b1100100010000 1
b1100100010000 G
b1100100010000 S
b100011110000000 N
b100011110 D
b0 E
b100011110000 I
b1000111100000 J
b10001111000000 M
b0 C
b1110111111100 !
b1110111111100 *
b1001011011001110 #
b1001011011001110 '
b11110010 $
b11110010 (
b11110010 ,
b10001111 "
b10001111 &
b10001111 +
b111 %
#80000
b0 5
b0 Z
b1000001010000000 4
b1000001010000000 _
b10110000001000 -
b10110000001000 [
b110000101000000 .
b110000101000000 V
b110000101000000 ]
b1011001010001000 )
b1011001010001000 3
b10000000000 6
b10000000000 U
b0 8
b0 K
b0 X
b110000000000000 7
b110000000000000 P
b110000000000000 Y
b101000000 9
b101000000 F
b101000000 W
b100110101001000 /
b100110101001000 Q
b100110101001000 \
b100111000000000 0
b100111000000000 L
b100111000000000 T
b1101001000 2
b1101001000 B
b1101001000 R
b0 1
b0 G
b0 S
b11101000 C
b1110100000 E
b0 D
b0 I
b0 J
b11101000000000 M
b111010000000000 N
b1111101111100100 !
b1111101111100100 *
b100100101011100 #
b100100101011100 '
b11000101 $
b11000101 (
b11000101 ,
b11101000 "
b11101000 &
b11101000 +
b1000 %
#85000
b1010000000 5
b1010000000 Z
b0 4
b0 _
b1101000101001 -
b1101000101001 [
b101000101000 .
b101000101000 V
b101000101000 ]
b10000100111001 )
b10000100111001 3
b10010010000 6
b10010010000 U
b0 7
b0 P
b0 Y
b101101000000 8
b101101000000 K
b101101000000 X
b1000000000001 /
b1000000000001 Q
b1000000000001 \
b101101000 9
b101101000 F
b101101000 W
b0 0
b0 L
b0 T
b1001001001000 1
b1001001001000 G
b1001001001000 S
b1001001001 2
b1001001001 B
b1001001001 R
b10111101000 H
b1011110100000 J
b1011110100 E
b0 M
b0 N
b10111101 C
b100011110011110 !
b100011110011110 *
b10011001100101 #
b10011001100101 '
b101101 $
b101101 (
b101101 ,
b10111101 "
b10111101 &
b10111101 +
b1001 %
#90000
b0 4
b0 _
b0 5
b0 Z
b1111011110 -
b1111011110 [
b1111011110 )
b1111011110 3
b0 6
b0 U
b0 .
b0 V
b0 ]
b1111011110 /
b1111011110 Q
b1111011110 \
b0 8
b0 K
b0 X
b0 9
b0 F
b0 W
b11000110 2
b11000110 B
b11000110 R
b1100011000 1
b1100011000 G
b1100011000 S
b11000110 D
b0 E
b1100011000 H
b0 J
b0 C
b10011001011110 !
b10011001011110 *
b10001010000000 #
b10001010000000 '
b1010 $
b1010 (
b1010 ,
b1100011 "
b1100011 &
b1100011 +
b1010 %
#95000
b1010101000000 )
b1010101000000 3
b1010101000000 -
b1010101000000 [
b1010101000000 /
b1010101000000 Q
b1010101000000 \
b1000000000000 0
b1000000000000 L
b1000000000000 T
b1000000 2
b1000000 B
b1000000 R
b10100000000 1
b10100000000 G
b10100000000 S
b10000000000 J
b1000000000000 N
b1000000 D
b100000000 H
b1110000111011101 !
b1110000111011101 *
b1100110010011101 #
b1100110010011101 '
b10101010 $
b10101010 (
b10101010 ,
b100000 "
b100000 &
b100000 +
b1011 %
#100000
b10000 4
b10000 _
b1000 .
b1000 V
b1000 ]
b1001000000 6
b1001000000 U
b101100100010 )
b101100100010 3
b100011010010 -
b100011010010 [
b1000 9
b1000 F
b1000 W
b100011011010 /
b100011011010 Q
b100011011010 \
b110111010 2
b110111010 B
b110111010 R
b0 0
b0 L
b0 T
b100101100000 1
b100101100000 G
b100101100000 S
b10010110 C
b100101100000 I
b100101100 D
b0 H
b0 J
b0 N
b100001100101111 !
b100001100101111 *
b11100000001101 #
b11100000001101 '
b10011 $
b10011 (
b10011 ,
b10010110 "
b10010110 &
b10010110 +
b1100 %
#105000
b100000001000 4
b100000001000 _
b1100011001001 -
b1100011001001 [
b10001010110001 )
b10001010110001 3
b111100000 6
b111100000 U
b10000000100 .
b10000000100 V
b10000000100 ]
b10000000000 8
b10000000000 K
b10000000000 X
b1110011001101 /
b1110011001101 Q
b1110011001101 \
b100 9
b100 F
b100 W
b1010011000000 0
b1010011000000 L
b1010011000000 T
b100011111000 1
b100011111000 G
b100011111000 S
b11110101 2
b11110101 B
b11110101 R
b1010011000 H
b101001100000 J
b1010011000000 M
b10100110 D
b0 I
b1010011 C
b100110110000110 !
b100110110000110 *
b10101011010101 #
b10101011010101 '
b1101011 $
b1101011 (
b1101011 ,
b1010011 "
b1010011 &
b1010011 +
b1101 %
#110000
b0 4
b0 _
b0 .
b0 V
b0 ]
b101011100 -
b101011100 [
b101011100 )
b101011100 3
b0 6
b0 U
b0 9
b0 F
b0 W
b0 8
b0 K
b0 X
b101011100 /
b101011100 Q
b101011100 \
b100000000 0
b100000000 L
b100000000 T
b1100 2
b1100 B
b1100 R
b1010000 1
b1010000 G
b1010000 S
b1000 E
b100000000 N
b100 D
b10000 H
b1000000 J
b0 M
b0 C
b1110101001111001 !
b1110101001111001 *
b1110100100011101 #
b1110100100011101 '
b10101110 $
b10101110 (
b10101110 ,
b10 "
b10 &
b10 +
b1110 %
#115000
b100000 4
b100000 _
b100011100 .
b100011100 V
b100011100 ]
b1010000000 6
b1010000000 U
b1110001001101 )
b1110001001101 3
b1100110101101 -
b1100110101101 [
b100011100 9
b100011100 F
b100011100 W
b1100010110001 /
b1100010110001 Q
b1100010110001 \
b0 0
b0 L
b0 T
b101010001 2
b101010001 B
b101010001 R
b1100111100000 1
b1100111100000 G
b1100111100000 S
b11001111 C
b110011110 D
b0 E
b0 H
b1100111100000 J
b0 N
b1000000101010111 !
b1000000101010111 *
b110010100001010 #
b110010100001010 '
b100011 $
b100011 (
b100011 ,
b11001111 "
b11001111 &
b11001111 +
b1111 %
#120000
b10000100000000 4
b10000100000000 _
b11001000000 6
b11001000000 U
b10111101011000 )
b10111101011000 3
b100000011000 -
b100000011000 [
b1100010000000 .
b1100010000000 V
b1100010000000 ]
b0 9
b0 F
b0 W
b1000010011000 /
b1000010011000 Q
b1000010011000 \
b1100010000000 8
b1100010000000 K
b1100010000000 X
b1100101000 2
b1100101000 B
b1100101000 R
b1001110110000 1
b1001110110000 G
b1001110110000 S
b1100101000 E
b11001010000 H
b110010100000 I
b0 D
b1100101000000 J
b0 C
b1110110101001010 !
b1110110101001010 *
b1011110111110010 #
b1011110111110010 '
b111100 $
b111100 (
b111100 ,
b11001010 "
b11001010 &
b11001010 +
b10000 %
#125000
b0 4
b0 _
b10001000001010 -
b10001000001010 [
b10001100001010 )
b10001100001010 3
b100000000 6
b100000000 U
b0 .
b0 V
b0 ]
b10001000001010 /
b10001000001010 Q
b10001000001010 \
b0 8
b0 K
b0 X
b10001010000000 0
b10001010000000 L
b10001010000000 T
b10001010 2
b10001010 B
b10001010 R
b0 1
b0 G
b0 S
b10001010 C
b10001010000000 M
b0 E
b0 H
b0 I
b0 J
b101011111100010 !
b101011111100010 *
b11010011011000 #
b11010011011000 '
b1000001 $
b1000001 (
b1000001 ,
b10001010 "
b10001010 &
b10001010 +
b10001 %
#130000
b11111110111000 -
b11111110111000 [
b100000000111000 )
b100000000111000 3
b10000000 6
b10000000 U
b11111110111000 /
b11111110111000 Q
b11111110111000 \
b1111000000 1
b1111000000 G
b1111000000 S
b11110000000000 0
b11110000000000 L
b11110000000000 T
b1111000 2
b1111000 B
b1111000 R
b1111000000 H
b11110000000000 N
b0 M
b1111000 C
b100111000100011 !
b100111000100011 *
b110111101011 #
b110111101011 '
b10001001 $
b10001001 (
b10001001 ,
b1111000 "
b1111000 &
b1111000 +
b10010 %
#135000
b10000000100000 4
b10000000100000 _
b110011110100100 -
b110011110100100 [
b1001010010000 .
b1001010010000 V
b1001010010000 ]
b10010000 9
b10010000 F
b10010000 W
b1000110011000100 )
b1000110011000100 3
b10100000000 6
b10100000000 U
b1001000000000 7
b1001000000000 P
b1001000000000 Y
b111010100110100 /
b111010100110100 Q
b111010100110100 \
b0 1
b0 G
b0 S
b111011010000000 0
b111011010000000 L
b111011010000000 T
b1110110100 2
b1110110100 B
b1110110100 R
b101101100 D
b1011011000 E
b10110110000000 M
b0 H
b101101100000000 N
b0 C
b1010000001110010 !
b1010000001110010 *
b1001110101110 #
b1001110101110 '
b11000110 $
b11000110 (
b11000110 ,
b10110110 "
b10110110 &
b10110110 +
b10011 %
#140000
b11000000000 4
b11000000000 _
b1100000011000 -
b1100000011000 [
b101100000000 .
b101100000000 V
b101100000000 ]
b1111011011000 )
b1111011011000 3
b11000000 6
b11000000 U
b0 9
b0 F
b0 W
b0 7
b0 P
b0 Y
b101100000000 8
b101100000000 K
b101100000000 X
b1001100011000 /
b1001100011000 Q
b1001100011000 \
b0 0
b0 L
b0 T
b1001001100000 1
b1001001100000 G
b1001001100000 S
b101111000 2
b101111000 B
b101111000 R
b10111100000 H
b1011110000000 J
b101111000 D
b0 E
b0 M
b0 N
b1011100011100011 !
b1011100011100011 *
b1001101000001011 #
b1001101000001011 '
b101010 $
b101010 (
b101010 ,
b10111100 "
b10111100 &
b10111100 +
b10100 %
#145000
b0 4
b0 _
b11100110110101 -
b11100110110101 [
b10000000 .
b10000000 V
b10000000 ]
b11101010110101 )
b11101010110101 3
b100000000 6
b100000000 U
b10000000 9
b10000000 F
b10000000 W
b11100100110101 /
b11100100110101 Q
b11100100110101 \
b0 8
b0 K
b0 X
b11100010000000 0
b11100010000000 L
b11100010000000 T
b110110101 2
b110110101 B
b110110101 R
b0 1
b0 G
b0 S
b1110001 C
b111000100 E
b11100010000000 N
b0 D
b0 H
b0 J
b1001000000000100 !
b1001000000000100 *
b101010101001111 #
b101010101001111 '
b10000101 $
b10000101 (
b10000101 ,
b1110001 "
b1110001 &
b1110001 +
b10101 %
#150000
b101011000000 4
b101011000000 _
b1010011110 -
b1010011110 [
b11111100000 .
b11111100000 V
b11111100000 ]
b110101011110 )
b110101011110 3
b0 6
b0 U
b11111100000 8
b11111100000 K
b11111100000 X
b10101111110 /
b10101111110 Q
b10101111110 \
b0 9
b0 F
b0 W
b0 0
b0 L
b0 T
b10100001000 1
b10100001000 G
b10100001000 S
b1110110 2
b1110110 B
b1110110 R
b1110110 D
b111011000 H
b1110110000 I
b11101100000 J
b0 E
b0 N
b0 C
b11111111011100 !
b11111111011100 *
b11001001111110 #
b11001001111110 '
b111010 $
b111010 (
b111010 ,
b111011 "
b111011 &
b111011 +
b10110 %
#155000
b0 4
b0 _
b110000100101 -
b110000100101 [
b1001111000101 )
b1001111000101 3
b11110100000 6
b11110100000 U
b0 .
b0 V
b0 ]
b110000100101 /
b110000100101 Q
b110000100101 \
b0 8
b0 K
b0 X
b111111000000 0
b111111000000 L
b111111000000 T
b10101 2
b10101 B
b10101 R
b1111110000 1
b1111110000 G
b1111110000 S
b10101 C
b10101000000 M
b101010000000 N
b0 D
b0 H
b101010000 I
b1010100000 J
b101111110011110 !
b101111110011110 *
b100101111011001 #
b100101111011001 '
b11110001 $
b11110001 (
b11110001 ,
b10101 "
b10101 &
b10101 +
b10111 %
#160000
b1101000011000 -
b1101000011000 [
b1110100011000 )
b1110100011000 3
b1100000000 6
b1100000000 U
b1101000011000 /
b1101000011000 Q
b1101000011000 \
b1100010000000 0
b1100010000000 L
b1100010000000 T
b110001000 2
b110001000 B
b110001000 R
b1100010000 1
b1100010000 G
b1100010000 S
b110001000 E
b1100010000 H
b0 I
b0 J
b1100010000000 M
b0 N
b0 C
b111001010110111 !
b111001010110111 *
b101010110011111 #
b101010110011111 '
b1001100 $
b1001100 (
b1001100 ,
b1100010 "
b1100010 &
b1100010 +
b11000 %
#165000
b1000000 4
b1000000 _
b1000000000 5
b1000000000 Z
b111111111001000 -
b111111111001000 [
b11011100000 .
b11011100000 V
b11011100000 ]
b1000101010001000 )
b1000101010001000 3
b100010000000 6
b100010000000 U
b11100000000 7
b11100000000 P
b11100000000 Y
b111100000 8
b111100000 K
b111100000 X
b111100100101000 /
b111100100101000 Q
b111100100101000 \
b110010001000000 0
b110010001000000 L
b110010001000000 T
b1110101101000 1
b1110101101000 G
b1110101101000 S
b0 2
b0 B
b0 R
b100011110000 I
b1000111100000 J
b100011110000000 N
b0 E
b10001111000 H
b10001111000000 M
b1110101100111111 !
b1110101100111111 *
b110000010110111 #
b110000010110111 '
b11111000 $
b11111000 (
b11111000 ,
b10001111 "
b10001111 &
b10001111 +
b11001 %
#170000
b101000000 4
b101000000 _
b0 5
b0 Z
b10100101010100 -
b10100101010100 [
b111100000 .
b111100000 V
b111100000 ]
b11100100100100 )
b11100100100100 3
b111010010000 6
b111010010000 U
b0 7
b0 P
b0 Y
b10100010110100 /
b10100010110100 Q
b10100010110100 \
b10011111000000 0
b10011111000000 L
b10011111000000 T
b1001111100 2
b1001111100 B
b1001111100 R
b110100001000 1
b110100001000 G
b110100001000 S
b1001111100 E
b10011111000 H
b100111110000 I
b0 J
b10011111000000 M
b0 N
b1111100101111111 !
b1111100101111111 *
b1100000001011011 #
b1100000001011011 '
b1011100 $
b1011100 (
b1011100 ,
b10011111 "
b10011111 &
b10011111 +
b11010 %
#175000
b0 4
b0 _
b0 .
b0 V
b0 ]
b10011010000001 -
b10011010000001 [
b10011100010001 )
b10011100010001 3
b10010000 6
b10010000 U
b0 8
b0 K
b0 X
b10011010000001 /
b10011010000001 Q
b10011010000001 \
b10001001000 1
b10001001000 G
b10001001000 S
b10001001000000 0
b10001001000000 L
b10001001000000 T
b10001001 2
b10001001 B
b10001001 R
b10001001 C
b0 E
b10001001000 H
b0 I
b10001001000000 M
b110010111100001 !
b110010111100001 *
b11111011010000 #
b11111011010000 '
b1001001 $
b1001001 (
b1001001 ,
b10001001 "
b10001001 &
b10001001 +
b11011 %
#180000
b11100001100111 -
b11100001100111 [
b100010000000111 )
b100010000000111 3
b101110100000 6
b101110100000 U
b11100001100111 /
b11100001100111 Q
b11100001100111 \
b110101110000 1
b110101110000 G
b110101110000 S
b11010111000000 0
b11010111000000 L
b11010111000000 T
b11010111 2
b11010111 B
b11010111 R
b110101110000 I
b0 H
b11010111000000 M
b11010111 C
b111001110011101 !
b111001110011101 *
b10111110010110 #
b10111110010110 '
b1010001 $
b1010001 (
b1010001 ,
b11010111 "
b11010111 &
b11010111 +
b11100 %
#185000
b100000000000 4
b100000000000 _
b100011000 -
b100011000 [
b10000000000 .
b10000000000 V
b10000000000 ]
b100100011000 )
b100100011000 3
b0 6
b0 U
b10000000000 7
b10000000000 P
b10000000000 Y
b10100011000 /
b10100011000 Q
b10100011000 \
b0 1
b0 G
b0 S
b10100000000 0
b10100000000 L
b10100000000 T
b11000 2
b11000 B
b11000 R
b11000 D
b11000000000 N
b0 I
b1100000000 M
b0 C
b1111011011100000 !
b1111011011100000 *
b1110110111001000 #
b1110110111001000 '
b11000010 $
b11000010 (
b11000010 ,
b1100 "
b1100 &
b1100 +
b11101 %
#190000
b1011000000000 4
b1011000000000 _
b101000000 5
b101000000 Z
b1010000 6
b1010000 U
b1110001011011 )
b1110001011011 3
b10011001011 -
b10011001011 [
b111101001000 .
b111101001000 V
b111101001000 ]
b0 7
b0 P
b0 Y
b10101000 9
b10101000 F
b10101000 W
b111111100000 8
b111111100000 K
b111111100000 X
b101110000011 /
b101110000011 Q
b101110000011 \
b0 0
b0 L
b0 T
b110101011 2
b110101011 B
b110101011 R
b101000101000 1
b101000101000 G
b101000101000 S
b1110111 C
b111011100 E
b1110111000 H
b11101110000 I
b111011100000 J
b0 D
b0 M
b0 N
b1111011101101101 !
b1111011101101101 *
b1101101100010010 #
b1101101100010010 '
b111101 $
b111101 (
b111101 ,
b1110111 "
b1110111 &
b1110111 +
b11110 %
#195000
b10001100000 4
b10001100000 _
b100000000 5
b100000000 Z
b1010101000110 -
b1010101000110 [
b11010110100110 )
b11010110100110 3
b1101100000000 6
b1101100000000 U
b11101110000 .
b11101110000 V
b11101110000 ]
b11110000000 8
b11110000000 K
b11110000000 X
b1001000110110 /
b1001000110110 Q
b1001000110110 \
b1111110000000 0
b1111110000000 L
b1111110000000 T
b11110000 9
b11110000 F
b11110000 W
b110000110 2
b110000110 B
b110000110 R
b110000110000 1
b110000110000 G
b110000110000 S
b1111110000000 M
b111111000 E
b1111110000 H
b0 I
b111111000000 J
b1111110 C
b1110011011111 !
b1110011011111 *
b1110011100111001 #
b1110011100111001 '
b1101101 $
b1101101 (
b1101101 ,
b1111110 "
b1111110 &
b1111110 +
b11111 %
