src/csa3_16.v
module csa3_16(
  input  [15:0] x,
  input  [15:0] y,
  input  [15:0] z,
  output [15:0] sum,
  output [15:0] carry_sh
);
  assign sum = x ^ y ^ z;
  assign carry_sh = ((x & y) | (y & z) | (x & z)) << 1;
endmodule

src/multiplier_wallace.v
// 8x8 Wallace-like multiplier using carry-save adder (CSA) tree
module multiplier_wallace(
    input  [7:0] a,
    input  [7:0] b,
    output [15:0] product
);

  // 16-bit shifted partial products
  wire [15:0] pp_shift [7:0];
  genvar k;
  generate
    for (k = 0; k < 8; k = k + 1) begin : gen_pp_shifts
      // extend a into 16 bits then shift by k
      assign pp_shift[k] = b[k] ? ({8'b0, a} << k) : 16'b0;
    end
  endgenerate

  // Stage 1: reduce groups of three partial products
  wire [15:0] s1, c1, s2, c2, s3, c3;
  csa3_16 u1 (pp_shift[0], pp_shift[1], pp_shift[2], s1, c1);
  csa3_16 u2 (pp_shift[3], pp_shift[4], pp_shift[5], s2, c2);
  csa3_16 u3 (pp_shift[6], pp_shift[7], 16'b0,          s3, c3);

  // Stage 2: reduce the stage-1 sums and the stage-1 carries
  wire [15:0] s4, c4, s5, c5;
  csa3_16 u4 (s1, s2, s3, s4, c4);
  csa3_16 u5 (c1, c2, c3, s5, c5); // c1/c2/c3 already include their left-shift

  // Stage 3: reduce the two resulting sums
  wire [15:0] s6, c6;
  csa3_16 u6 (s4, s5, 16'b0, s6, c6);

  // Final: add remaining operands (s6 + c4 + c5 + c6). All carries produced by CSA are left-shifted.
  assign product = s6 + c4 + c5 + c6;

endmodule

// 3:2 carry-save adder for 16-bit vectors.
// sum = x ^ y ^ z
// carry_sh = ((x&y) | (y&z) | (x&z)) << 1  (carry bits shifted to next weight)

tb/tb_multiplier_wallace.v
`timescale 1ns/1ps

module tb_multiplier_wallace;

    reg  [7:0] a, b;
    wire [15:0] product;

    // Instantiate DUT
    multiplier_wallace uut (
        .a(a),
        .b(b),
        .product(product)
    );

    integer i;

    initial begin
        $dumpfile("waves/multiplier_wallace.vcd");
        $dumpvars(0, tb_multiplier_wallace);

        // Test vectors
        a = 8'd0;   b = 8'd0;   #10;
        a = 8'd5;   b = 8'd7;   #10;
        a = 8'd10;  b = 8'd14;  #10;
        a = 8'd25;  b = 8'd3;   #10;
        a = 8'd55;  b = 8'd22;  #10;
        a = 8'd100; b = 8'd12;  #10;
        a = 8'd255; b = 8'd1;   #10;
        a = 8'd255; b = 8'd255; #10;

         // Random exhaustive-ish tests (not full 65536 but many)
        for (i = 0; i < 2000; i = i + 1) begin
            a = $random % 256;
            b = $random % 256;
            #1;
            if (product !== ((a+0)*(b+0))) begin
                $display("ERROR: a=%0d b=%0d product=%0d expected=%0d", a, b, product, ((a+0)*(b+0)));
                $finish;
            end
            #4;
        end

        $display("All random checks passed.");
        $finish;
    end

endmodule

waves/multiplier_wallace.vcd
$date
	Mon Nov 17 10:12:10 2025
$end
$version
	Icarus Verilog
$end
$timescale
	1ps
$end
$scope module tb_multiplier_wallace $end
$var wire 16 ! product [15:0] $end
$var reg 8 " a [7:0] $end
$var reg 8 # b [7:0] $end
$var integer 32 $ i [31:0] $end
$scope module uut $end
$var wire 8 % a [7:0] $end
$var wire 8 & b [7:0] $end
$var wire 16 ' s6 [15:0] $end
$var wire 16 ( s5 [15:0] $end
$var wire 16 ) s4 [15:0] $end
$var wire 16 * s3 [15:0] $end
$var wire 16 + s2 [15:0] $end
$var wire 16 , s1 [15:0] $end
$var wire 16 - product [15:0] $end
$var wire 16 . c6 [15:0] $end
$var wire 16 / c5 [15:0] $end
$var wire 16 0 c4 [15:0] $end
$var wire 16 1 c3 [15:0] $end
$var wire 16 2 c2 [15:0] $end
$var wire 16 3 c1 [15:0] $end
$scope begin gen_pp_shifts[0] $end
$var parameter 2 4 k $end
$upscope $end
$scope begin gen_pp_shifts[1] $end
$var parameter 2 5 k $end
$upscope $end
$scope begin gen_pp_shifts[2] $end
$var parameter 3 6 k $end
$upscope $end
$scope begin gen_pp_shifts[3] $end
$var parameter 3 7 k $end
$upscope $end
$scope begin gen_pp_shifts[4] $end
$var parameter 4 8 k $end
$upscope $end
$scope begin gen_pp_shifts[5] $end
$var parameter 4 9 k $end
$upscope $end
$scope begin gen_pp_shifts[6] $end
$var parameter 4 : k $end
$upscope $end
$scope begin gen_pp_shifts[7] $end
$var parameter 4 ; k $end
$upscope $end
$scope module u1 $end
$var wire 16 < sum [15:0] $end
$var wire 16 = x [15:0] $end
$var wire 16 > y [15:0] $end
$var wire 16 ? z [15:0] $end
$var wire 16 @ carry_sh [15:0] $end
$upscope $end
$scope module u2 $end
$var wire 16 A sum [15:0] $end
$var wire 16 B x [15:0] $end
$var wire 16 C y [15:0] $end
$var wire 16 D z [15:0] $end
$var wire 16 E carry_sh [15:0] $end
$upscope $end
$scope module u3 $end
$var wire 16 F sum [15:0] $end
$var wire 16 G x [15:0] $end
$var wire 16 H y [15:0] $end
$var wire 16 I z [15:0] $end
$var wire 16 J carry_sh [15:0] $end
$upscope $end
$scope module u4 $end
$var wire 16 K sum [15:0] $end
$var wire 16 L x [15:0] $end
$var wire 16 M y [15:0] $end
$var wire 16 N z [15:0] $end
$var wire 16 O carry_sh [15:0] $end
$upscope $end
$scope module u5 $end
$var wire 16 P sum [15:0] $end
$var wire 16 Q x [15:0] $end
$var wire 16 R y [15:0] $end
$var wire 16 S z [15:0] $end
$var wire 16 T carry_sh [15:0] $end
$upscope $end
$scope module u6 $end
$var wire 16 U sum [15:0] $end
$var wire 16 V x [15:0] $end
$var wire 16 W y [15:0] $end
$var wire 16 X z [15:0] $end
$var wire 16 Y carry_sh [15:0] $end
$upscope $end
$upscope $end
$upscope $end
$enddefinitions $end
$comment Show the parameter values. $end
$dumpall
b111 ;
b110 :
b101 9
b100 8
b11 7
b10 6
b1 5
b0 4
$end
#0
$dumpvars
b0 Y
b0 X
b0 W
b0 V
b0 U
b0 T
b0 S
b0 R
b0 Q
b0 P
b0 O
b0 N
b0 M
b0 L
b0 K
b0 J
b0 I
b0 H
b0 G
b0 F
b0 E
b0 D
b0 C
b0 B
b0 A
b0 @
b0 ?
b0 >
b0 =
b0 <
b0 3
b0 2
b0 1
b0 0
b0 /
b0 .
b0 -
b0 ,
b0 +
b0 *
b0 )
b0 (
b0 '
b0 &
b0 %
bx $
b0 #
b0 "
b0 !
$end
#10000
b10000 .
b10000 Y
b100011 !
b100011 -
b10011 '
b10011 U
b1000 (
b1000 P
b1000 W
b11011 )
b11011 K
b11011 V
b1000 3
b1000 @
b1000 Q
b11011 ,
b11011 <
b11011 L
b101 =
b1010 >
b10100 ?
b111 #
b111 &
b101 "
b101 %
#20000
b0 .
b0 Y
b100000 0
b100000 O
b10001100 !
b10001100 -
b1101100 '
b1101100 U
b0 (
b0 P
b0 W
b1101100 )
b1101100 K
b1101100 V
b1010000 +
b1010000 A
b1010000 M
b0 3
b0 @
b0 Q
b111100 ,
b111100 <
b111100 L
b1010000 B
b10100 >
b101000 ?
b0 =
b1110 #
b1110 &
b1010 "
b1010 %
#30000
b1000000 .
b1000000 Y
b100000 (
b100000 P
b100000 W
b1011 '
b1011 U
b1001011 !
b1001011 -
b0 0
b0 O
b100000 3
b100000 @
b100000 Q
b101011 )
b101011 K
b101011 V
b0 +
b0 A
b0 M
b101011 ,
b101011 <
b101011 L
b11001 =
b110010 >
b0 ?
b0 B
b11 #
b11 &
b11001 "
b11001 %
#40000
b100000000 .
b100000000 Y
b1100000 0
b1100000 O
b10010111010 !
b10010111010 -
b1101011010 '
b1101011010 U
b10011000 (
b10011000 P
b10011000 W
b1111000010 )
b1111000010 K
b1111000010 V
b10011000 3
b10011000 @
b10011000 Q
b1101110000 +
b1101110000 A
b1101110000 M
b10110010 ,
b10110010 <
b10110010 L
b11011100 ?
b1101110000 C
b1101110 >
b0 =
b10110 #
b10110 &
b110111 "
b110111 %
#50000
b0 .
b0 Y
b0 (
b0 P
b0 W
b1010110000 '
b1010110000 U
b10010110000 !
b10010110000 -
b1000000000 0
b1000000000 O
b0 3
b0 @
b0 Q
b1010110000 )
b1010110000 K
b1010110000 V
b1100100000 +
b1100100000 A
b1100100000 M
b110010000 ,
b110010000 <
b110010000 L
b1100100000 B
b0 >
b110010000 ?
b0 C
b1100 #
b1100 &
b1100100 "
b1100100 %
#60000
b11111111 '
b11111111 U
b11111111 !
b11111111 -
b0 0
b0 O
b11111111 )
b11111111 K
b11111111 V
b0 +
b0 A
b0 M
b11111111 ,
b11111111 <
b11111111 L
b11111111 =
b0 ?
b0 B
b1 #
b1 &
b11111111 "
b11111111 %
#70000
b1000001000101000 .
b1000001000101000 Y
b11111111000000 /
b11111111000000 T
b10111010000 0
b10111010000 O
b1111111000000001 !
b1111111000000001 -
b11011001001001 '
b11011001001001 U
b110001100011100 (
b110001100011100 P
b110001100011100 W
b111111100000000 1
b111111100000000 J
b111111100000000 S
b1111111100 3
b1111111100 @
b1111111100 Q
b1111111100000 2
b1111111100000 E
b1111111100000 R
b101010101010101 )
b101010101010101 K
b101010101010101 V
b100000001000000 *
b100000001000000 F
b100000001000000 N
b1011111101 ,
b1011111101 <
b1011111101 L
b1011111101000 +
b1011111101000 A
b1011111101000 M
b111111110 >
b1111111100 ?
b11111111000 B
b111111110000 C
b1111111100000 D
b11111111000000 G
b111111110000000 H
b11111111 #
b11111111 &
#80000
b0 /
b0 T
b0 .
b0 Y
b1001000100100 '
b1001000100100 U
b0 (
b0 P
b0 W
b1001000100100 !
b1001000100100 -
b0 0
b0 O
b0 2
b0 E
b0 R
b0 1
b0 J
b0 S
b0 3
b0 @
b0 Q
b1001000100100 )
b1001000100100 K
b1001000100100 V
b1001000000000 *
b1001000000000 F
b1001000000000 N
b100100 ,
b100100 <
b100100 L
b0 +
b0 A
b0 M
b0 >
b0 ?
b0 B
b0 C
b0 D
b0 G
b1001000000000 H
b100100 =
b10000001 #
b10000001 &
b100100 "
b100100 %
b0 $
#85000
b1101111011 !
b1101111011 -
b1101111011 '
b1101111011 U
b1101111011 )
b1101111011 K
b1101111011 V
b1001000000 *
b1001000000 F
b1001000000 N
b100100000 +
b100100000 A
b100100000 M
b11011 ,
b11011 <
b11011 L
b10010 >
b100100000 D
b1001000000 G
b0 H
b1001 =
b1100011 #
b1100011 &
b1001 "
b1001 %
b1 $
#90000
b1010000 0
b1010000 O
b1000 (
b1000 P
b1000 W
b11100101001 !
b11100101001 -
b11011011001 '
b11011011001 U
b1000 3
b1000 @
b1000 Q
b11011010001 )
b11011010001 K
b11011010001 V
b11010000000 *
b11010000000 F
b11010000000 N
b111001 ,
b111001 <
b111001 L
b1101000 +
b1101000 A
b1101000 M
b110100 ?
b1101000 B
b11010000000 H
b0 >
b0 D
b0 G
b1101 =
b10001101 #
b10001101 &
b1101 "
b1101 %
b10 $
#95000
b10000000 0
b10000000 O
b11100011010 !
b11100011010 -
b11010011010 '
b11010011010 U
b0 (
b0 P
b0 W
b11010011010 )
b11010011010 K
b11010011010 V
b0 3
b0 @
b0 Q
b11001010000 +
b11001010000 A
b11001010000 M
b0 *
b0 F
b0 N
b11001010 ,
b11001010 <
b11001010 L
b11001010 >
b11001010000 C
b0 ?
b0 B
b0 H
b0 =
b10010 #
b10010 &
b1100101 "
b1100101 %
b11 $
#100000
b1101 '
b1101 U
b1101 !
b1101 -
b0 0
b0 O
b1101 )
b1101 K
b1101 V
b1000 +
b1000 A
b1000 M
b101 ,
b101 <
b101 L
b1 =
b100 ?
b1000 B
b0 >
b0 C
b1101 #
b1101 &
b1 "
b1 %
b100 $
#105000
b1011001000000 .
b1011001000000 Y
b100000000 /
b100000000 T
b1110000011110 !
b1110000011110 -
b10011011110 '
b10011011110 U
b111101100000 (
b111101100000 P
b111101100000 W
b101110111110 )
b101110111110 K
b101110111110 V
b111111000000 2
b111111000000 E
b111111000000 R
b10100000 3
b10100000 @
b10100000 Q
b101000010000 +
b101000010000 A
b101000010000 M
b110101110 ,
b110101110 <
b110101110 L
b11101100000 C
b111011000000 D
b111011000 ?
b1110110000 B
b1110110 =
b111101 #
b111101 &
b1110110 "
b1110110 %
b101 $
#110000
b0 .
b0 Y
b0 /
b0 T
b111001001011100 '
b111001001011100 U
b1000000110011100 !
b1000000110011100 -
b111101000000 0
b111101000000 O
b0 (
b0 P
b0 W
b111001001011100 )
b111001001011100 K
b111001001011100 V
b0 2
b0 E
b0 R
b111011010000000 *
b111011010000000 F
b111011010000000 N
b0 3
b0 @
b0 Q
b1110110100 ,
b1110110100 <
b1110110100 L
b11101101000 +
b11101101000 A
b11101101000 M
b111011010000000 H
b1110110100 ?
b11101101000 B
b0 C
b0 D
b0 =
b10001100 #
b10001100 &
b11101101 "
b11101101 %
b110 $
#115000
b1000000110000000 .
b1000000110000000 Y
b11101100010110 '
b11101100010110 U
b111101111000000 (
b111101111000000 P
b111101111000000 W
b1100000010010110 !
b1100000010010110 -
b10000000000 0
b10000000000 O
b1111000000 3
b1111000000 @
b1111000000 Q
b111100000000000 1
b111100000000000 J
b111100000000000 S
b100000011010110 )
b100000011010110 K
b100000011010110 V
b0 +
b0 A
b0 M
b100001011000000 *
b100001011000000 F
b100001011000000 N
b1000010110 ,
b1000010110 <
b1000010110 L
b111110010 >
b11111001000000 G
b1111100100 ?
b0 B
b111110010000000 H
b11000110 #
b11000110 &
b11111001 "
b11111001 %
b111 $
#120000
b0 .
b0 Y
b111110111000010 '
b111110111000010 U
b1000000 (
b1000000 P
b1000000 W
b1000001011010010 !
b1000001011010010 -
b10100010000 0
b10100010000 O
b0 3
b0 @
b0 Q
b0 1
b0 J
b0 S
b1000000 2
b1000000 E
b1000000 R
b111110110000010 )
b111110110000010 K
b111110110000010 V
b110001010000000 *
b110001010000000 F
b110001010000000 N
b1111010001000 +
b1111010001000 A
b1111010001000 M
b110001010 ,
b110001010 <
b110001010 L
b11000101000 B
b1100010100000 D
b110001010 >
b0 ?
b0 G
b110001010000000 H
b10101010 #
b10101010 &
b11000101 "
b11000101 %
b1000 $
#125000
b1001000010000 .
b1001000010000 Y
b1101110001000 (
b1101110001000 P
b1101110001000 W
b11001010000011 '
b11001010000011 U
b110101001110011 !
b110101001110011 -
b10010111100000 0
b10010111100000 O
b1110001000 3
b1110001000 @
b1110001000 Q
b1100000000000 2
b1100000000000 E
b1100000000000 R
b10100100001011 )
b10100100001011 K
b10100100001011 V
b11100101000000 *
b11100101000000 F
b11100101000000 N
b1010111011 ,
b1010111011 <
b1010111011 L
b1001011110000 +
b1001011110000 A
b1001011110000 M
b11100101 =
b1110010100 ?
b111001010000 C
b11100101000000 G
b111001010 >
b0 B
b1110010100000 D
b0 H
b1110111 #
b1110111 &
b11100101 "
b11100101 %
b1001 $
#130000
b0 .
b0 Y
b100000 0
b100000 O
b101000001110 !
b101000001110 -
b100111101110 '
b100111101110 U
b0 (
b0 P
b0 W
b0 2
b0 E
b0 R
b100111101110 )
b100111101110 K
b100111101110 V
b0 3
b0 @
b0 Q
b100100000000 *
b100100000000 F
b100100000000 N
b1111110 ,
b1111110 <
b1111110 L
b10010000 +
b10010000 A
b10010000 M
b10010000 B
b100100000000 H
b100100 >
b1001000 ?
b0 C
b0 D
b0 G
b10010 =
b10001111 #
b10001111 &
b10010 "
b10010 %
b1010 $
#135000
b1000000000000000 .
b1000000000000000 Y
b11001110111100 '
b11001110111100 U
b111001110000000 (
b111001110000000 P
b111001110000000 W
b1100001010111100 !
b1100001010111100 -
b111100000000 0
b111100000000 O
b111000000000000 1
b111000000000000 J
b111000000000000 S
b100000000111100 )
b100000000111100 K
b100000000111100 V
b1110000000 3
b1110000000 @
b1110000000 Q
b11110010000 +
b11110010000 A
b11110010000 M
b100010110000000 *
b100010110000000 F
b100010110000000 N
b1000101100 ,
b1000101100 <
b1000101100 L
b11110010000000 G
b111100100 >
b1111001000 ?
b11110010000 B
b111100100000000 H
b0 =
b11001110 #
b11001110 &
b11110010 "
b11110010 %
b1011 $
#140000
b1000001010000000 .
b1000001010000000 Y
b10000000000 0
b10000000000 O
b1011001010001000 !
b1011001010001000 -
b10110000001000 '
b10110000001000 U
b110000101000000 (
b110000101000000 P
b110000101000000 W
b110000000000000 1
b110000000000000 J
b110000000000000 S
b101000000 3
b101000000 @
b101000000 Q
b100110101001000 )
b100110101001000 K
b100110101001000 V
b0 +
b0 A
b0 M
b100111000000000 *
b100111000000000 F
b100111000000000 N
b1101001000 ,
b1101001000 <
b1101001000 L
b11101000 =
b0 >
b1110100000 ?
b0 B
b11101000000000 G
b111010000000000 H
b11000101 #
b11000101 &
b11101000 "
b11101000 %
b1100 $
#145000
b100000000 /
b100000000 T
b11000000000 .
b11000000000 Y
b10010010101100 '
b10010010101100 U
b11100100000 (
b11100100000 P
b11100100000 W
b100001111101100 !
b100001111101100 -
b1100001000000 0
b1100001000000 O
b0 1
b0 J
b0 S
b11110000000 2
b11110000000 E
b11110000000 R
b10001110001100 )
b10001110001100 K
b10001110001100 V
b10100000 3
b10100000 @
b10100000 Q
b10111000000000 *
b10111000000000 F
b10111000000000 N
b110010100000 +
b110010100000 A
b110010100000 M
b100101100 ,
b100101100 <
b100101100 L
b1011100000 B
b10111000000 C
b101110000000 D
b101110000 ?
b0 G
b10111000000000 H
b1011100 =
b10111101 #
b10111101 &
b1011100 "
b1011100 %
b1101 $
#150000
b10010000 .
b10010000 Y
b0 /
b0 T
b1100000000 0
b1100000000 O
b1000111000001 !
b1000111000001 -
b111000110001 '
b111000110001 U
b1001000 (
b1001000 P
b1001000 W
b0 2
b0 E
b0 R
b111001111001 )
b111001111001 K
b111001111001 V
b1001000 3
b1001000 @
b1001000 Q
b101101000000 *
b101101000000 F
b101101000000 N
b10011001 ,
b10011001 <
b10011001 L
b10110100000 +
b10110100000 A
b10110100000 M
b101101000000 G
b10110100 ?
b0 B
b0 C
b10110100000 D
b0 H
b101101 =
b1100101 #
b1100101 &
b101101 "
b101101 %
b1110 $
#155000
b0 .
b0 Y
b0 0
b0 O
b1111011110 !
b1111011110 -
b1111011110 '
b1111011110 U
b0 (
b0 P
b0 W
b1111011110 )
b1111011110 K
b1111011110 V
b0 3
b0 @
b0 Q
b0 *
b0 F
b0 N
b11000110 ,
b11000110 <
b11000110 L
b1100011000 +
b1100011000 A
b1100011000 M
b11000110 >
b1100011000 B
b0 ?
b0 D
b0 G
b0 =
b1010 #
b1010 &
b1100011 "
b1100011 %
b1111 $
#160000
b1000000000000 !
b1000000000000 -
b1000000000000 '
b1000000000000 U
b1000000000000 )
b1000000000000 K
b1000000000000 V
b0 ,
b0 <
b0 L
b1000000000000 +
b1000000000000 A
b1000000000000 M
b1000000000000 D
b0 >
b0 B
b100000 #
b100000 &
b10000000 "
b10000000 %
b10000 $
#165000
b10100000 .
b10100000 Y
b111000000000 0
b111000000000 O
b101010000 (
b101010000 P
b101010000 W
b110100001000010 !
b110100001000010 -
b101100110100010 '
b101100110100010 U
b101010000 3
b101010000 @
b101010000 Q
b101100011110010 )
b101100011110010 K
b101100011110010 V
b101010100000000 *
b101010100000000 F
b101010100000000 N
b1000000010 ,
b1000000010 <
b1000000010 L
b111111110000 +
b111111110000 A
b111111110000 M
b10101010 =
b1010101000 ?
b10101010000 B
b101010100000 C
b101010100000000 H
b0 D
b10011101 #
b10011101 &
b10101010 "
b10101010 %
b10001 $
#170000
b10000 .
b10000 Y
b1001000000 0
b1001000000 O
b101100100010 !
b101100100010 -
b100011010010 '
b100011010010 U
b1000 (
b1000 P
b1000 W
b100011011010 )
b100011011010 K
b100011011010 V
b1000 3
b1000 @
b1000 Q
b100101100000 +
b100101100000 A
b100101100000 M
b0 *
b0 F
b0 N
b110111010 ,
b110111010 <
b110111010 L
b100101100 >
b0 ?
b0 B
b100101100000 C
b0 H
b10010110 =
b10011 #
b10011 &
b10010110 "
b10010110 %
b10010 $
#175000
b0 .
b0 Y
b1110010111 '
b1110010111 U
b10000110111 !
b10000110111 -
b10100000 0
b10100000 O
b10000 (
b10000 P
b10000 W
b1110000111 )
b1110000111 K
b1110000111 V
b10000 3
b10000 @
b10000 Q
b1101000000 *
b1101000000 F
b1101000000 N
b11010000 +
b11010000 A
b11010000 M
b10111 ,
b10111 <
b10111 L
b1101000000 G
b11010 >
b11010000 C
b1101 =
b1010011 #
b1010011 &
b1101 "
b1101 %
b10011 $
#180000
b100000000100000 .
b100000000100000 Y
b100101100111 '
b100101100111 U
b10000101010000 (
b10000101010000 P
b10000101010000 W
b101100100000111 !
b101100100000111 -
b111110000000 0
b111110000000 O
b10000100000000 1
b10000100000000 J
b10000100000000 S
b1010000 3
b1010000 @
b1010000 Q
b10100000110111 )
b10100000110111 K
b10100000110111 V
b11010110000 +
b11010110000 A
b11010110000 M
b10111101000000 *
b10111101000000 F
b10111101000000 N
b111000111 ,
b111000111 <
b111000111 L
b110101100 ?
b11010110000000 H
b0 >
b11010110000 C
b1101011000000 G
b1101011 =
b11010101 #
b11010101 &
b1101011 "
b1101011 %
b10100 $
#185000
b0 .
b0 Y
b101011100 '
b101011100 U
b0 (
b0 P
b0 W
b101011100 !
b101011100 -
b0 0
b0 O
b0 1
b0 J
b0 S
b101011100 )
b101011100 K
b101011100 V
b0 3
b0 @
b0 Q
b100000000 *
b100000000 F
b100000000 N
b1010000 +
b1010000 A
b1010000 M
b1100 ,
b1100 <
b1100 L
b100 >
b10000 B
b1000000 D
b1000 ?
b0 C
b0 G
b100000000 H
b0 =
b10101110 #
b10101110 &
b10 "
b10 %
b10101 $
#190000
b1000011110000 .
b1000011110000 Y
b10100000011 '
b10100000011 U
b110001111000 (
b110001111000 P
b110001111000 W
b1011101110011 !
b1011101110011 -
b110000000 0
b110000000 O
b110000000000 1
b110000000000 J
b110000000000 S
b1111000 3
b1111000 @
b1111000 Q
b100101111011 )
b100101111011 K
b100101111011 V
b100111000000 *
b100111000000 F
b100111000000 N
b1010011 ,
b1010011 <
b1010011 L
b11101000 +
b11101000 A
b11101000 M
b11101 =
b11101000000 G
b111010 >
b1110100 ?
b11101000 B
b0 D
b111010000000 H
b11001111 #
b11001111 &
b11101 "
b11101 %
b10110 $
#195000
b0 .
b0 Y
b0 0
b0 O
b101011110 !
b101011110 -
b101011110 '
b101011110 U
b0 (
b0 P
b0 W
b0 1
b0 J
b0 S
b101011110 )
b101011110 K
b101011110 V
b0 3
b0 @
b0 Q
b100011000 +
b100011000 A
b100011000 M
b0 *
b0 F
b0 N
b1000110 ,
b1000110 <
b1000110 L
b1000110 >
b0 ?
b100011000 B
b0 G
b0 H
b0 =
b1010 #
b1010 &
b100011 "
b100011 %
b10111 $
#200000
b10000100000000 .
b10000100000000 Y
b100000011000 '
b100000011000 U
b10111101011000 !
b10111101011000 -
b11001000000 0
b11001000000 O
b1100010000000 (
b1100010000000 P
b1100010000000 W
b1000010011000 )
b1000010011000 K
b1000010011000 V
b1100010000000 2
b1100010000000 E
b1100010000000 R
b1100101000 ,
b1100101000 <
b1100101000 L
b1001110110000 +
b1001110110000 A
b1001110110000 M
b1100101000 ?
b110010100000 C
b1100101000000 D
b0 >
b11001010000 B
b111100 #
b111100 &
b11001010 "
b11001010 %
b11000 $
#205000
b0 .
b0 Y
b111111101110100 '
b111111101110100 U
b1000001001110100 !
b1000001001110100 -
b1100000000 0
b1100000000 O
b0 (
b0 P
b0 W
b111111101110100 )
b111111101110100 K
b111111101110100 V
b0 2
b0 E
b0 R
b111100100000000 *
b111100100000000 F
b111100100000000 N
b111100100 ,
b111100100 <
b111100100 L
b11110010000 +
b11110010000 A
b11110010000 M
b111100100 >
b111100100000000 H
b0 ?
b11110010000 B
b0 C
b0 D
b10001010 #
b10001010 &
b11110010 "
b11110010 %
b11001 $
#210000
b0 0
b0 O
b11011011011000 !
b11011011011000 -
b11011011011000 '
b11011011011000 U
b11011011011000 )
b11011011011000 K
b11011011011000 V
b0 ,
b0 <
b0 L
b11000011000 +
b11000011000 A
b11000011000 M
b11000011000000 *
b11000011000000 F
b11000011000000 N
b10000010000 C
b1000001000000 G
b0 >
b1000001000 B
b10000010000000 H
b11011000 #
b11011000 &
b1000001 "
b1000001 %
b11010 $
#215000
b10000000 0
b10000000 O
b100000000111000 !
b100000000111000 -
b11111110111000 '
b11111110111000 U
b11111110111000 )
b11111110111000 K
b11111110111000 V
b1111000 ,
b1111000 <
b1111000 L
b1111000000 +
b1111000000 A
b1111000000 M
b11110000000000 *
b11110000000000 F
b11110000000000 N
b1111000 =
b1111000000 B
b0 C
b0 G
b11110000000000 H
b10001001 #
b10001001 &
b1111000 "
b1111000 %
b11011 $
#220000
b10000 .
b10000 Y
b1101101001000 (
b1101101001000 P
b1101101001000 W
b111111101100010 '
b111111101100010 U
b1100001000 3
b1100001000 @
b1100001000 Q
b1100001000000 2
b1100001000000 E
b1100001000000 R
b1010011100010010 !
b1010011100010010 -
b10011110100000 0
b10011110100000 O
b110010000101010 )
b110010000101010 K
b110010000101010 V
b111010110000000 *
b111010110000000 F
b111010110000000 N
b1001111010000 +
b1001111010000 A
b1001111010000 M
b1001111010 ,
b1001111010 <
b1001111010 L
b111010110 >
b1110101100 ?
b111010110000 C
b1110101100000 D
b0 B
b111010110000000 H
b0 =
b10110110 #
b10110110 &
b11101011 "
b11101011 %
b11100 $
#225000
b10000000000 .
b10000000000 Y
b1000010000 (
b1000010000 P
b1000010000 W
b111110101110100 '
b111110101110100 U
b1000011010010100 !
b1000011010010100 -
b10100100000 0
b10100100000 O
b1000010000 3
b1000010000 @
b1000010000 Q
b0 2
b0 E
b0 R
b111111101100100 )
b111111101100100 K
b111111101100100 V
b110001100000000 *
b110001100000000 F
b110001100000000 N
b1010010100 ,
b1010010100 <
b1010010100 L
b1111011110000 +
b1111011110000 A
b1111011110000 M
b11000110000 B
b110001100 >
b1100011000 ?
b0 C
b1100011000000 D
b110001100000000 H
b10101110 #
b10101110 &
b11000110 "
b11000110 %
b11101 $
#230000
b0 /
b0 T
b11000000000 .
b11000000000 Y
b101100000000 (
b101100000000 P
b101100000000 W
b1100000011000 '
b1100000011000 U
b1111011011000 !
b1111011011000 -
b11000000 0
b11000000 O
b0 3
b0 @
b0 Q
b101100000000 2
b101100000000 E
b101100000000 R
b1001100011000 )
b1001100011000 K
b1001100011000 V
b0 *
b0 F
b0 N
b101111000 ,
b101111000 <
b101111000 L
b1001001100000 +
b1001001100000 A
b1001001100000 M
b101111000 >
b0 ?
b10111100000 B
b1011110000000 D
b0 H
b101010 #
b101010 &
b10111100 "
b10111100 %
b11110 $
#235000
b0 .
b0 Y
b1101011011 '
b1101011011 U
b10011011011 !
b10011011011 -
b110000000 0
b110000000 O
b1000000 (
b1000000 P
b1000000 W
b1100011011 )
b1100011011 K
b1100011011 V
b1000000 2
b1000000 E
b1000000 R
b1011000000 *
b1011000000 F
b1011000000 N
b1011 ,
b1011 <
b1011 L
b111010000 +
b111010000 A
b111010000 M
b1011 =
b10110000 C
b1011000000 G
b0 >
b0 B
b101100000 D
b1110001 #
b1110001 &
b1011 "
b1011 %
b11111 $
#240000
b0 .
b0 Y
b1000 (
b1000 P
b1000 W
b1000010000 0
b1000010000 O
b10100100001011 !
b10100100001011 -
b10011011111011 '
b10011011111011 U
b0 2
b0 E
b0 R
b1000 3
b1000 @
b1000 Q
b10011011110011 )
b10011011110011 K
b10011011110011 V
b10000101000000 *
b10000101000000 F
b10000101000000 N
b1110011011 ,
b1110011011 <
b1110011011 L
b10000101000 +
b10000101000 A
b10000101000 M
b100001010 >
b1000010100 ?
b10000101000 B
b0 C
b0 D
b10000101000000 G
b10000101 =
b1001111 #
b1001111 &
b10000101 "
b10000101 %
b100000 $
#245000
b101011000000 .
b101011000000 Y
b0 /
b0 T
b1010011110 '
b1010011110 U
b11111100000 (
b11111100000 P
b11111100000 W
b110101011110 !
b110101011110 -
b0 0
b0 O
b11111100000 2
b11111100000 E
b11111100000 R
b10101111110 )
b10101111110 K
b10101111110 V
b0 3
b0 @
b0 Q
b0 *
b0 F
b0 N
b10100001000 +
b10100001000 A
b10100001000 M
b1110110 ,
b1110110 <
b1110110 L
b1110110000 C
b11101100000 D
b1110110 >
b0 ?
b111011000 B
b0 G
b0 =
b111010 #
b111010 &
b111011 "
b111011 %
b100001 $
#250000
b11000000 .
b11000000 Y
b0 /
b0 T
b1100000000 0
b1100000000 O
b101001010110 !
b101001010110 -
b11010010110 '
b11010010110 U
b11110000 (
b11110000 P
b11110000 W
b11110000 3
b11110000 @
b11110000 Q
b11001100110 )
b11001100110 K
b11001100110 V
b0 2
b0 E
b0 R
b110000110 ,
b110000110 <
b110000110 L
b11111100000 +
b11111100000 A
b11111100000 M
b1111110 =
b111111000 ?
b0 >
b0 B
b11111100000 C
b0 D
b10101 #
b10101 &
b1111110 "
b1111110 %
b100010 $
#255000
b1001100000000000 .
b1001100000000000 Y
b11001010101001 '
b11001010101001 U
b1100110001001001 !
b1100110001001001 -
b110100000 0
b110100000 O
b111000000000000 1
b111000000000000 J
b111000000000000 S
b111111000000000 (
b111111000000000 P
b111111000000000 W
b111000000000 2
b111000000000 E
b111000000000 R
b100110010101001 )
b100110010101001 K
b100110010101001 V
b100010011000000 *
b100010011000000 F
b100010011000000 N
b0 3
b0 @
b0 Q
b100010011000 +
b100010011000 A
b100010011000 M
b11110001 ,
b11110001 <
b11110001 L
b11110001000 B
b11110001000000 G
b111100010000000 H
b0 ?
b111100010000 C
b11110001 =
b11011001 #
b11011001 &
b11110001 "
b11110001 %
b100011 $
