src/csa3_16.v
module csa3_16(
  input  [15:0] x,
  input  [15:0] y,
  input  [15:0] z,
  output [15:0] sum,
  output [15:0] carry_sh
);
  assign sum = x ^ y ^ z;
  assign carry_sh = ((x & y) | (y & z) | (x & z)) << 1;
endmodule

src/multiplier_wallace.v
// 8x8 Wallace-like multiplier using carry-save adder (CSA) tree
module multiplier_wallace(
    input  [7:0] a,
    input  [7:0] b,
    output [15:0] product
);

  // 16-bit shifted partial products
  wire [15:0] pp_shift [7:0];
  genvar k;
  generate
    for (k = 0; k < 8; k = k + 1) begin : gen_pp_shifts
      // extend a into 16 bits then shift by k
      assign pp_shift[k] = b[k] ? ({8'b0, a} << k) : 16'b0;
    end
  endgenerate

  // Stage 1: reduce groups of three partial products
  wire [15:0] s1, c1, s2, c2, s3, c3;
  csa3_16 u1 (pp_shift[0], pp_shift[1], pp_shift[2], s1, c1);
  csa3_16 u2 (pp_shift[3], pp_shift[4], pp_shift[5], s2, c2);
  csa3_16 u3 (pp_shift[6], pp_shift[7], 16'b0,          s3, c3);

  // Stage 2: reduce the stage-1 sums and the stage-1 carries
  wire [15:0] s4, c4, s5, c5;
  csa3_16 u4 (s1, s2, s3, s4, c4);
  csa3_16 u5 (c1, c2, c3, s5, c5); // c1/c2/c3 already include their left-shift

  // Stage 3: reduce the two resulting sums
  wire [15:0] s6, c6;
  csa3_16 u6 (s4, s5, 16'b0, s6, c6);

  // Final: add remaining operands (s6 + c4 + c5 + c6). All carries produced by CSA are left-shifted.
  assign product = s6 + c4 + c5 + c6;

endmodule

// 3:2 carry-save adder for 16-bit vectors.
// sum = x ^ y ^ z
// carry_sh = ((x&y) | (y&z) | (x&z)) << 1  (carry bits shifted to next weight)

src/mac_unit.v
`timescale 1ns/1ps
module mac_unit (
    input  [7:0]  a,
    input  [7:0]  b,
    input  [15:0] acc,
    output [15:0] mac_out
);

    wire [15:0] product;

    // Use your Wallace multiplier
    multiplier_wallace mul (
        .a(a),
        .b(b),
        .product(product)
    );

    assign mac_out = product + acc;

endmodule

// This is intentionally simple — because for now we focus on functional comparison.
// Later we will add CLA adder + pipelining enhancements.

tb/tb_mac.v
`timescale 1ns/1ps

module tb_mac;

    reg  [7:0]  a, b;
    reg  [15:0] acc;
    wire [15:0] mac_out;

    integer i;

    // Instantiate MAC Unit
    mac_unit DUT (
        .a(a),
        .b(b),
        .acc(acc),
        .mac_out(mac_out)
    );

    initial begin
        $dumpfile("waves/mac_unit.vcd");
        $dumpvars(0, tb_mac);

        // Directed Tests
        a = 8'd5; b = 8'd10; acc = 16'd20; #10;
        a = 8'd15; b = 8'd3; acc = 16'd7;   #10;
        a = 8'd255; b = 8'd1; acc = 16'd0;  #10;
        a = 8'd100; b = 8'd2; acc = 16'd50; #10;

        // Random Tests
        for (i = 0; i < 2000; i = i + 1) begin
            a   = $random % 256;
            b   = $random % 256;
            acc = $random % 65536;
            #1;
            if (mac_out !== (a * b + acc)) begin
                $display("ERROR: a=%0d b=%0d acc=%0d mac_out=%0d expected=%0d",
                         a, b, acc, mac_out, (a*b + acc));
                $finish;
            end
            #4;
        end

        $display("All MAC tests passed!");
        #100 $finish;
    end

endmodule

MAC/MAC.sim/sim_1/behav/xsim/dump.vcd
$date
   Mon Nov 17 11:50:33 2025
$end

$version
  2024.2.0
$end

$timescale
  1ps
$end

$scope module tb_mac $end
$var reg 8 ! a [7:0] $end
$var reg 8 " b [7:0] $end
$var reg 16 # acc [15:0] $end
$var wire 16 $ mac_out [15:0] $end
$var integer 32 % i [31:0] $end
$scope module DUT $end
$var wire 8 & a [7:0] $end
$var wire 8 ' b [7:0] $end
$var wire 16 ( acc [15:0] $end
$var wire 16 $ mac_out [15:0] $end
$var wire 16 ) product [15:0] $end
$scope module mul $end
$var wire 8 & a [7:0] $end
$var wire 8 ' b [7:0] $end
$var wire 16 ) product [15:0] $end
$var wire 16 * s1 [15:0] $end
$var wire 16 + c1 [15:0] $end
$var wire 16 , s2 [15:0] $end
$var wire 16 - c2 [15:0] $end
$var wire 16 . s3 [15:0] $end
$var wire 16 / c3 [15:0] $end
$var wire 16 0 s4 [15:0] $end
$var wire 16 1 c4 [15:0] $end
$var wire 16 2 s5 [15:0] $end
$var wire 16 3 c5 [15:0] $end
$var wire 16 4 s6 [15:0] $end
$var wire 16 5 c6 [15:0] $end
$scope module u1 $end
$var wire 16 6 x [15:0] $end
$var wire 16 7 y [31:16] $end
$var wire 16 8 z [47:32] $end
$var wire 16 * sum [15:0] $end
$var wire 16 + carry_sh [15:0] $end
$upscope $end
$scope module u2 $end
$var wire 16 9 x [63:48] $end
$var wire 16 : y [79:64] $end
$var wire 16 ; z [95:80] $end
$var wire 16 , sum [15:0] $end
$var wire 16 - carry_sh [15:0] $end
$upscope $end
$scope module u3 $end
$var wire 16 < x [111:96] $end
$var wire 16 = y [127:112] $end
$var wire 16 > z [15:0] $end
$var wire 16 . sum [15:0] $end
$var wire 16 / carry_sh [15:0] $end
$upscope $end
$scope module u4 $end
$var wire 16 * x [15:0] $end
$var wire 16 , y [15:0] $end
$var wire 16 . z [15:0] $end
$var wire 16 0 sum [15:0] $end
$var wire 16 1 carry_sh [15:0] $end
$upscope $end
$scope module u5 $end
$var wire 16 + x [15:0] $end
$var wire 16 - y [15:0] $end
$var wire 16 / z [15:0] $end
$var wire 16 2 sum [15:0] $end
$var wire 16 3 carry_sh [15:0] $end
$upscope $end
$scope module u6 $end
$var wire 16 0 x [15:0] $end
$var wire 16 2 y [15:0] $end
$var wire 16 ? z [15:0] $end
$var wire 16 4 sum [15:0] $end
$var wire 16 5 carry_sh [15:0] $end
$upscope $end
$upscope $end
$upscope $end
$upscope $end
$enddefinitions $end

#0
$dumpvars
b101 !
b1010 "
b10100 #
b1000110 $
bx %
b101 &
b1010 '
b10100 (
b110010 )
b1010 *
b0 +
b101000 ,
b0 -
b0 .
b0 /
b100010 0
b10000 1
b0 2
b0 3
b100010 4
b0 5
b0 6
b1010 7
b0 8
b101000 9
b0 :
b0 ;
b0 <
b0 =
b0 >
b0 ?
$end

#10000
b1111 !
b11 "
b111 #
b110100 $
b1111 &
b11 '
b111 (
b101101 )
b10001 *
b11100 +
b0 ,
b10001 0
b0 1
b11100 2
b1101 4
b100000 5
b1111 6
b11110 7
b0 9

#20000
b11111111 !
b1 "
b0 #
b11111111 $
b11111111 &
b1 '
b0 (
b11111111 )
b11111111 *
b0 +
b11111111 0
b0 2
b11111111 4
b0 5
b11111111 6
b0 7

#30000
b1100100 !
b10 "
b110010 #
b11111010 $
b1100100 &
b10 '
b110010 (
b11001000 )
b11001000 *
b11001000 0
b11001000 4
b0 6
b11001000 7

#40000
b100100 !
b10000001 "
b1101011000001001 #
b1110100000101101 $
b0 %
b100100 &
b10000001 '
b1101011000001001 (
b1001000100100 )
b100100 *
b1001000000000 .
b1001000100100 0
b1001000100100 4
b100100 6
b0 7
b1001000000000 =

#45000
b1100011 !
b1101 "
b1001100110001101 #
b1001111010010100 $
b1 %
b1100011 &
b1101 '
b1001100110001101 (
b10100000111 )
b111101111 *
b1100011000 ,
b0 .
b1011110111 0
b1000010000 1
b1011110111 4
b1100011 6
b110001100 8
b1100011000 9
b0 =

#50000
b1100101 !
b10010 "
b1110001100000001 #
b1110101000011011 $
b10 %
b1100101 &
b10010 '
b1110001100000001 (
b11100011010 )
b11001010 *
b11001010000 ,
b11010011010 0
b10000000 1
b11010011010 4
b0 6
b11001010 7
b0 8
b0 9
b11001010000 :

#55000
b1101 !
b1110110 "
b1100110100111101 #
b1101001100111011 $
b11 %
b1101 &
b1110110 '
b1100110100111101 (
b10111111110 )
b101110 *
b100000 +
b101110000 ,
b100000000 -
b1101000000 .
b1000011110 0
b1011000000 1
b100100000 2
b1100111110 4
b11010 7
b110100 8
b11010000 :
b110100000 ;
b1101000000 <

#60000
b11101101 !
b10001100 "
b1110100111111001 #
b110101110010101 $
b100 %
b11101101 &
b10001100 '
b1110100111111001 (
b1000000110011100 )
b1110110100 *
b0 +
b11101101000 ,
b0 -
b111011010000000 .
b111001001011100 0
b111101000000 1
b0 2
b111001001011100 4
b0 7
b1110110100 8
b11101101000 9
b0 :
b0 ;
b0 <
b111011010000000 =

#65000
b11000110 !
b11000101 "
b1101001010101010 #
b110101100001000 $
b101 %
b11000110 &
b11000101 '
b1101001010101010 (
b1001100001011110 )
b1111011110 *
b0 ,
b101001010000000 .
b100001000000000 /
b101000101011110 0
b10100000000 1
b100001000000000 2
b1001101011110 4
b1000000000000000 5
b11000110 6
b1100011000 8
b0 9
b11000110000000 <
b110001100000000 =

#70000
b11100101 !
b1110111 "
b1101011000010010 #
b100000010000101 $
b110 %
b11100101 &
b1110111 '
b1101011000010010 (
b110101001110011 )
b1010111011 *
b1110001000 +
b1001011110000 ,
b1100000000000 -
b11100101000000 .
b0 /
b10100100001011 0
b10010111100000 1
b1101110001000 2
b11001010000011 4
b1001000010000 5
b11100101 6
b111001010 7
b1110010100 8
b111001010000 :
b1110010100000 ;
b11100101000000 <
b0 =

#75000
b10001111 !
b11110010 "
b1001011011001110 #
b1110111111100 $
b111 %
b10001111 &
b11110010 '
b1001011011001110 (
b1000011100101110 )
b100011110 *
b0 +
b1100100010000 ,
b111000000 -
b110010001000000 .
b11100000000 /
b111110001001110 0
b1000100000 1
b11011000000 2
b1000000000 3
b111101010001110 4
b100010000000 5
b0 6
b100011110 7
b0 8
b100011110000 :
b1000111100000 ;
b10001111000000 <
b100011110000000 =

#80000
b11101000 !
b11000101 "
b100100101011100 #
b1111101111100100 $
b1000 %
b11101000 &
b11000101 '
b100100101011100 (
b1011001010001000 )
b1101001000 *
b101000000 +
b0 ,
b0 -
b100111000000000 .
b110000000000000 /
b100110101001000 0
b10000000000 1
b110000101000000 2
b0 3
b10110000001000 4
b1000001010000000 5
b11101000 6
b0 7
b1110100000 8
b0 :
b0 ;
b11101000000000 <
b111010000000000 =

#85000
b10111101 !
b101101 "
b10011001100101 #
b100011110011110 $
b1001 %
b10111101 &
b101101 '
b10011001100101 (
b10000100111001 )
b1001001001 *
b101101000 +
b1001001001000 ,
b101101000000 -
b0 .
b0 /
b1000000000001 0
b10010010000 1
b101000101000 2
b1010000000 3
b1101000101001 4
b0 5
b10111101 6
b1011110100 8
b10111101000 9
b1011110100000 ;
b0 <
b0 =

#90000
b1100011 !
b1010 "
b10001010000000 #
b10011001011110 $
b1010 %
b1100011 &
b1010 '
b10001010000000 (
b1111011110 )
b11000110 *
b0 +
b1100011000 ,
b0 -
b1111011110 0
b0 1
b0 2
b0 3
b1111011110 4
b0 6
b11000110 7
b0 8
b1100011000 9
b0 ;

#95000
b100000 !
b10101010 "
b1100110010011101 #
b1110000111011101 $
b1011 %
b100000 &
b10101010 '
b1100110010011101 (
b1010101000000 )
b1000000 *
b10100000000 ,
b1000000000000 .
b1010101000000 0
b1010101000000 4
b1000000 7
b100000000 9
b10000000000 ;
b1000000000000 =

#100000
b10010110 !
b10011 "
b11100000001101 #
b100001100101111 $
b1100 %
b10010110 &
b10011 '
b11100000001101 (
b101100100010 )
b110111010 *
b1000 +
b100101100000 ,
b0 .
b100011011010 0
b1001000000 1
b1000 2
b100011010010 4
b10000 5
b10010110 6
b100101100 7
b0 9
b100101100000 :
b0 ;
b0 =

#105000
b1010011 !
b1101011 "
b10101011010101 #
b100110110000110 $
b1101 %
b1010011 &
b1101011 '
b10101011010101 (
b10001010110001 )
b11110101 *
b100 +
b100011111000 ,
b10000000000 -
b1010011000000 .
b1110011001101 0
b111100000 1
b10000000100 2
b1100011001001 4
b100000001000 5
b1010011 6
b10100110 7
b1010011000 9
b0 :
b101001100000 ;
b1010011000000 <

#110000
b10 !
b10101110 "
b1110100100011101 #
b1110101001111001 $
b1110 %
b10 &
b10101110 '
b1110100100011101 (
b101011100 )
b1100 *
b0 +
b1010000 ,
b0 -
b100000000 .
b101011100 0
b0 1
b0 2
b101011100 4
b0 5
b0 6
b100 7
b1000 8
b10000 9
b1000000 ;
b0 <
b100000000 =

#115000
b11001111 !
b100011 "
b110010100001010 #
b1000000101010111 $
b1111 %
b11001111 &
b100011 '
b110010100001010 (
b1110001001101 )
b101010001 *
b100011100 +
b1100111100000 ,
b0 .
b1100010110001 0
b1010000000 1
b100011100 2
b1100110101101 4
b100000 5
b11001111 6
b110011110 7
b0 8
b0 9
b1100111100000 ;
b0 =

#120000
b11001010 !
b111100 "
b1011110111110010 #
b1110110101001010 $
b10000 %
b11001010 &
b111100 '
b1011110111110010 (
b10111101011000 )
b1100101000 *
b0 +
b1001110110000 ,
b1100010000000 -
b1000010011000 0
b11001000000 1
b1100010000000 2
b100000011000 4
b10000100000000 5
b0 6
b0 7
b1100101000 8
b11001010000 9
b110010100000 :
b1100101000000 ;

#125000
b10001010 !
b1000001 "
b11010011011000 #
b101011111100010 $
b10001 %
b10001010 &
b1000001 '
b11010011011000 (
b10001100001010 )
b10001010 *
b0 ,
b0 -
b10001010000000 .
b10001000001010 0
b100000000 1
b0 2
b10001000001010 4
b0 5
b10001010 6
b0 8
b0 9
b0 :
b0 ;
b10001010000000 <

#130000
b1111000 !
b10001001 "
b110111101011 #
b100111000100011 $
b10010 %
b1111000 &
b10001001 '
b110111101011 (
b100000000111000 )
b1111000 *
b1111000000 ,
b11110000000000 .
b11111110111000 0
b10000000 1
b11111110111000 4
b1111000 6
b1111000000 9
b0 <
b11110000000000 =

#135000
b10110110 !
b11000110 "
b1001110101110 #
b1010000001110010 $
b10011 %
b10110110 &
b11000110 '
b1001110101110 (
b1000110011000100 )
b1110110100 *
b10010000 +
b0 ,
b111011010000000 .
b1001000000000 /
b111010100110100 0
b10100000000 1
b1001010010000 2
b110011110100100 4
b10000000100000 5
b0 6
b101101100 7
b1011011000 8
b0 9
b10110110000000 <
b101101100000000 =

#140000
b10111100 !
b101010 "
b1001101000001011 #
b1011100011100011 $
b10100 %
b10111100 &
b101010 '
b1001101000001011 (
b1111011011000 )
b101111000 *
b0 +
b1001001100000 ,
b101100000000 -
b0 .
b0 /
b1001100011000 0
b11000000 1
b101100000000 2
b1100000011000 4
b11000000000 5
b101111000 7
b0 8
b10111100000 9
b1011110000000 ;
b0 <
b0 =

#145000
b1110001 !
b10000101 "
b101010101001111 #
b1001000000000100 $
b10101 %
b1110001 &
b10000101 '
b101010101001111 (
b11101010110101 )
b110110101 *
b10000000 +
b0 ,
b0 -
b11100010000000 .
b11100100110101 0
b100000000 1
b10000000 2
b11100110110101 4
b0 5
b1110001 6
b0 7
b111000100 8
b0 9
b0 ;
b11100010000000 =

#150000
b111011 !
b111010 "
b11001001111110 #
b11111111011100 $
b10110 %
b111011 &
b111010 '
b11001001111110 (
b110101011110 )
b1110110 *
b0 +
b10100001000 ,
b11111100000 -
b0 .
b10101111110 0
b0 1
b11111100000 2
b1010011110 4
b101011000000 5
b0 6
b1110110 7
b0 8
b111011000 9
b1110110000 :
b11101100000 ;
b0 =

#155000
b10101 !
b11110001 "
b100101111011001 #
b101111110011110 $
b10111 %
b10101 &
b11110001 '
b100101111011001 (
b1001111000101 )
b10101 *
b1111110000 ,
b0 -
b111111000000 .
b110000100101 0
b11110100000 1
b0 2
b110000100101 4
b0 5
b10101 6
b0 7
b0 9
b101010000 :
b1010100000 ;
b10101000000 <
b101010000000 =

#160000
b1100010 !
b1001100 "
b101010110011111 #
b111001010110111 $
b11000 %
b1100010 &
b1001100 '
b101010110011111 (
b1110100011000 )
b110001000 *
b1100010000 ,
b1100010000000 .
b1101000011000 0
b1100000000 1
b1101000011000 4
b0 6
b110001000 8
b1100010000 9
b0 :
b0 ;
b1100010000000 <
b0 =

#165000
b10001111 !
b11111000 "
b110000010110111 #
b1110101100111111 $
b11001 %
b10001111 &
b11111000 '
b110000010110111 (
b1000101010001000 )
b0 *
b1110101101000 ,
b111100000 -
b110010001000000 .
b11100000000 /
b111100100101000 0
b100010000000 1
b11011100000 2
b1000000000 3
b111111111001000 4
b1000000 5
b0 8
b10001111000 9
b100011110000 :
b1000111100000 ;
b10001111000000 <
b100011110000000 =

#170000
b10011111 !
b1011100 "
b1100000001011011 #
b1111100101111111 $
b11010 %
b10011111 &
b1011100 '
b1100000001011011 (
b11100100100100 )
b1001111100 *
b110100001000 ,
b10011111000000 .
b0 /
b10100010110100 0
b111010010000 1
b111100000 2
b0 3
b10100101010100 4
b101000000 5
b1001111100 8
b10011111000 9
b100111110000 :
b0 ;
b10011111000000 <
b0 =

#175000
b10001001 !
b1001001 "
b11111011010000 #
b110010111100001 $
b11011 %
b10001001 &
b1001001 '
b11111011010000 (
b10011100010001 )
b10001001 *
b10001001000 ,
b0 -
b10001001000000 .
b10011010000001 0
b10010000 1
b0 2
b10011010000001 4
b0 5
b10001001 6
b0 8
b10001001000 9
b0 :
b10001001000000 <

#180000
b11010111 !
b1010001 "
b10111110010110 #
b111001110011101 $
b11100 %
b11010111 &
b1010001 '
b10111110010110 (
b100010000000111 )
b11010111 *
b110101110000 ,
b11010111000000 .
b11100001100111 0
b101110100000 1
b11100001100111 4
b11010111 6
b0 9
b110101110000 :
b11010111000000 <

#185000
b1100 !
b11000010 "
b1110110111001000 #
b1111011011100000 $
b11101 %
b1100 &
b11000010 '
b1110110111001000 (
b100100011000 )
b11000 *
b0 ,
b10100000000 .
b10000000000 /
b10100011000 0
b0 1
b10000000000 2
b100011000 4
b100000000000 5
b0 6
b11000 7
b0 :
b1100000000 <
b11000000000 =

#190000
b1110111 !
b111101 "
b1101101100010010 #
b1111011101101101 $
b11110 %
b1110111 &
b111101 '
b1101101100010010 (
b1110001011011 )
b110101011 *
b10101000 +
b101000101000 ,
b111111100000 -
b0 .
b0 /
b101110000011 0
b1010000 1
b111101001000 2
b101000000 3
b10011001011 4
b1011000000000 5
b1110111 6
b0 7
b111011100 8
b1110111000 9
b11101110000 :
b111011100000 ;
b0 <
b0 =

#195000
b1111110 !
b1101101 "
b1110011100111001 #
b1110011011111 $
b11111 %
b1111110 &
b1101101 '
b1110011100111001 (
b11010110100110 )
b110000110 *
b11110000 +
b110000110000 ,
b11110000000 -
b1111110000000 .
b1001000110110 0
b1101100000000 1
b11101110000 2
b100000000 3
b1010101000110 4
b10001100000 5
b1111110 6
b111111000 8
b1111110000 9
b0 :
b111111000000 ;
b1111110000000 <

#200000
b11111 !
b11010011 "
b10111110000101 #
b100100100010010 $
b100000 %
b11111 &
b11010011 '
b10111110000101 (
b1100110001101 )
b100001 *
b111100 +
b111110000 ,
b0 -
b100001000000 .
b111100000000 /
b100110010001 0
b11000000 1
b111100111100 2
b0 3
b11010101101 4
b1001000100000 5
b11111 6
b111110 7
b0 8
b0 9
b111110000 :
b0 ;
b11111000000 <
b111110000000 =

#205000
b1111000 !
b1011011 "
b100101101001001 #
b111010111110001 $
b100001 %
b1111000 &
b1011011 '
b100101101001001 (
b10101010101000 )
b10001000 *
b11100000 +
b10001000000 ,
b11100000000 -
b1111000000000 .
b0 /
b1101011001000 0
b100000000000 1
b11111100000 2
b1110100101000 4
b10110000000 5
b1111000 6
b11110000 7
b1111000000 9
b11110000000 :
b1111000000000 <
b0 =

#210000
b111111 !
b101010 "
b110001101011000 #
b110110110101110 $
b100010 %
b111111 &
b101010 '
b110001101011000 (
b101001010110 )
b1111110 *
b0 +
b11000011000 ,
b1111000000 -
b0 .
b11001100110 0
b110000 1
b1111000000 2
b10110100110 4
b10010000000 5
b0 6
b1111110 7
b111111000 9
b0 :
b11111100000 ;
b0 <

#215000
b10000110 !
b10001110 "
b1111001010011100 #
b11110011110000 $
b100011 %
b10000110 &
b10001110 '
b1111001010011100 (
b100101001010100 )
b1100010100 *
b10000 +
b10000110000 ,
b0 -
b100001100000000 .
b100010000100100 0
b11000100000 1
b10000 2
b100010000110100 4
b0 5
b100001100 7
b1000011000 8
b10000110000 9
b0 ;
b100001100000000 =

#220000
b11111010 !
b100110 "
b1011101110011 #
b11110010001111 $
b100100 %
b11111010 &
b100110 '
b1011101110011 (
b10010100011100 )
b1000011100 *
b1111000000 +
b1111101000000 ,
b0 .
b1110101011100 0
b10000000000 1
b1111000000 2
b1111010011100 4
b1010000000 5
b111110100 7
b1111101000 8
b0 9
b1111101000000 ;
b0 =

#225000
b10100011 !
b101111 "
b1001001010110011 #
b1011000010100000 $
b100101 %
b10100011 &
b101111 '
b1001001010110011 (
b1110111101101 )
b1101101001 *
b100001100 +
b1000101111000 ,
b100000000000 -
b1001000010001 0
b1011010000 1
b100100001100 2
b1101100011101 4
b0 5
b10100011 6
b101000110 7
b1010001100 8
b10100011000 9
b1010001100000 ;

#230000
b1011111 !
b1000100 "
b1111110111110111 #
b1011100110011 $
b100110 %
b1011111 &
b1000100 '
b1111110111110111 (
b1100100111100 )
b101111100 *
b0 +
b0 ,
b0 -
b1011111000000 .
b1011010111100 0
b1010000000 1
b0 2
b1011010111100 4
b0 6
b0 7
b101111100 8
b0 9
b0 ;
b1011111000000 <

#235000
b11001011 !
b11100110 "
b1101101101011010 #
b1001000110111100 $
b100111 %
b11001011 &
b11100110 '
b1101101101011010 (
b1011011001100010 )
b1010111010 *
b1000001000 +
b1100101100000 ,
b101011101000000 .
b100000100000000 /
b100110010011010 0
b10011011000000 1
b100001100001000 2
b111110010010 4
b1000000000010000 5
b110010110 7
b1100101100 8
b1100101100000 ;
b11001011000000 <
b110010110000000 =

#240000
b101001 !
b11101101 "
b110110011011010 #
b1001001011001111 $
b101000 %
b101001 &
b11101101 '
b110110011011010 (
b10010111110101 )
b10001101 *
b1000000 +
b10001101000 ,
b1000000000 -
b1111011000000 .
b0 /
b1101000100101 0
b100110010000 1
b1001000000 2
b1100001100101 4
b10000000000 5
b101001 6
b0 7
b10100100 8
b101001000 9
b10100100000 ;
b101001000000 <
b1010010000000 =

#245000
b1100101 !
b10110101 "
b1001010011011111 #
b1101110001001000 $
b101001 %
b1100101 &
b10110101 '
b1001010011011111 (
b100011101101001 )
b111110001 *
b1000 +
b101011110000 ,
b100000000000 -
b11001010000000 .
b11100110000001 0
b10111100000 1
b100000001000 2
b11000110001001 4
b1000000000000 5
b1100101 6
b110010100 8
b0 9
b11001010000 :
b110010100000 ;
b0 <
b11001010000000 =

#250000
b1111001 !
b1000100 "
b110011010000 #
b10110011110100 $
b101010 %
b1111001 &
b1000100 '
b110011010000 (
b10000000100100 )
b111100100 *
b0 +
b0 ,
b0 -
b1111001000000 .
b1111110100100 0
b10000000 1
b0 2
b1111110100100 4
b0 5
b0 6
b111100100 8
b0 :
b0 ;
b1111001000000 <
b0 =

#255000
b101010 !
b10101011 "
b1100111100001110 #
b1110101100011100 $
b101011 %
b101010 &
b10101011 '
b1100111100001110 (
b1110000001110 )
b1111110 *
b10000010000 ,
b1010000000 -
b1010100000000 .
b1000101101110 0
b100000100000 1
b1010000000 2
b1001111101110 4
b101010 6
b1010100 7
b0 8
b101010000 9
b10101000000 ;
b0 <
b1010100000000 =

#260000
b11011100 !
b10011010 "
b111001011111101 #
b1111011101010101 $
b101100 %
b11011100 &
b10011010 '
b111001011111101 (
b1000010001011000 )
b110111000 *
b101100100000 ,
b100110000000 -
b110111000000000 .
b110010010011000 0
b1011001000000 1
b100110000000 2
b110110100011000 4
b100000000 5
b0 6
b110111000 7
b11011100000 9
b110111000000 :
b0 ;
b110111000000000 =

#265000
b11000011 !
b1010110 "
b1110100101001110 #
b10101011010000 $
b101101 %
b11000011 &
b1010110 '
b1110100101001110 (
b100000110000010 )
b1010001010 *
b1000001000 +
b110000110000 ,
b0 -
b11000011000000 .
b11111001111010 0
b100000000 1
b1000001000 2
b11110001110010 4
b10000010000 5
b110000110 7
b1100001100 8
b0 9
b110000110000 :
b11000011000000 <
b0 =

#270000
b1100111 !
b1010 "
b1011100110110110 #
b1011110110111100 $
b101110 %
b1100111 &
b1010 '
b1011100110110110 (
b10000000110 )
b11001110 *
b0 +
b1100111000 ,
b0 .
b1111110110 0
b10000 1
b0 2
b1111110110 4
b0 5
b11001110 7
b0 8
b1100111000 9
b0 :
b0 <

#275000
b111000 !
b1111001 "
b1100010010111000 #
b1101111100110000 $
b101111 %
b111000 &
b1111001 '
b1100010010111000 (
b1101001111000 )
b111000 *
b10101000000 ,
b11100000000 -
b111000000000 .
b101101111000 0
b100000000000 1
b11100000000 2
b110001111000 4
b11000000000 5
b111000 6
b0 7
b111000000 9
b1110000000 :
b11100000000 ;
b111000000000 <

#280000
b10010100 !
b10010011 "
b10110000000100 #
b1000000100000000 $
b110000 %
b10010100 &
b10010011 '
b10110000000100 (
b101010011111100 )
b110111100 *
b100101000000 ,
b0 -
b100101000000000 .
b100001011111100 0
b1001000000000 1
b0 2
b100001011111100 4
b0 5
b10010100 6
b100101000 7
b0 9
b100101000000 :
b0 ;
b0 <
b100101000000000 =

#285000
b1011001 !
b11011011 "
b1101111001001101 #
b10101001110000 $
b110001 %
b1011001 &
b11011011 '
b1101111001001101 (
b100110000100011 )
b11101011 *
b100000 +
b11101011000 ,
b100000000 -
b11101011000000 .
b100000000000 /
b11110101110011 0
b10110010000 1
b100100100000 2
b11010001010011 4
b1001001000000 5
b1011001 6
b10110010 7
b1011001000 9
b10110010000 :
b1011001000000 <
b10110010000000 =

#290000
b11011001 !
b1101101 "
b1110001001110110 #
b11111011011011 $
b110010 %
b11011001 &
b1101101 '
b1110001001110110 (
b101110001100101 )
b1110111101 *
b10000000 +
b1110111101000 ,
b10000000000 -
b11011001000000 .
b0 /
b10100000010101 0
b10111111010000 1
b10010000000 2
b10110010010101 4
b0 5
b11011001 6
b0 7
b1101100100 8
b11011001000 9
b0 :
b1101100100000 ;
b11011001000000 <
b0 =

#295000
b11001010 !
b10110110 "
b111000110010101 #
b100110001 $
b110011 %
b11001010 &
b10110110 '
b111000110010101 (
b1000111110011100 )
b1010111100 *
b1000000000 +
b1010111100000 ,
b1000000000000 -
b110010100000000 .
b111001001011100 0
b101101000000 1
b1001000000000 2
b110000001011100 4
b10010000000000 5
b0 6
b110010100 7
b1100101000 8
b0 9
b110010100000 :
b1100101000000 ;
b0 <
b110010100000000 =

#300000
b1000110 !
b100 "
b110000111110111 #
b110001100001111 $
b110100 %
b1000110 &
b100 '
b110000111110111 (
b100011000 )
b100011000 *
b0 +
b0 ,
b0 -
b0 .
b100011000 0
b0 1
b0 2
b100011000 4
b0 5
b0 7
b100011000 8
b0 :
b0 ;
b0 =

#305000
b1101001 !
b10110100 "
b1000110110001000 #
b1101011101011100 $
b110101 %
b1101001 &
b10110100 '
b1000110110001000 (
b100100111010100 )
b110100100 *
b101110110000 ,
b100000000000 -
b11010010000000 .
b11111010010100 0
b1101000000 1
b100000000000 2
b11011010010100 4
b1000000000000 5
b110100100 8
b11010010000 :
b110100100000 ;
b11010010000000 =

#310000
b101000 !
b101101 "
b11000011000111 #
b11011111001111 $
b110110 %
b101000 &
b101101 '
b11000011000111 (
b11100001000 )
b10001000 *
b1000000 +
b10001000000 ,
b1000000000 -
b0 .
b10011001000 0
b0 1
b1001000000 2
b11010001000 4
b10000000 5
b101000 6
b10100000 8
b101000000 9
b0 :
b10100000000 ;
b0 =

#315000
b101110 !
b1000 "
b100010100011100 #
b100011010001100 $
b110111 %
b101110 &
b1000 '
b100010100011100 (
b101110000 )
b0 *
b0 +
b101110000 ,
b0 -
b101110000 0
b0 2
b101110000 4
b0 5
b0 6
b0 8
b101110000 9
b0 ;

#320000
b11111101 !
b101001 "
b1001000000011100 #
b1011100010100001 $
b111000 %
b11111101 &
b101001 '
b1001000000011100 (
b10100010000101 )
b11111101 *
b1100001001000 ,
b111101000000 -
b1100010110101 0
b10010000 1
b111101000000 2
b1011111110101 4
b1000000000000 5
b11111101 6
b11111101000 9
b1111110100000 ;

#325000
b10000110 !
b11011010 "
b1100011000111101 #
b11100001011001 $
b111001 %
b10000110 &
b11011010 '
b1100011000111101 (
b111001000011100 )
b100001100 *
b110001010000 ,
b1000000 -
b110001010000000 .
b1000000000 /
b110111111011100 0
b0 1
b1001000000 2
b110110110011100 4
b10010000000 5
b0 6
b100001100 7
b10000110000 9
b100001100000 :
b0 ;
b10000110000000 <
b100001100000000 =

#330000
b1100110 !
b1110000 "
b10001110011 #
b11000100010011 $
b111010 %
b1100110 &
b1110000 '
b10001110011 (
b10110010100000 )
b0 *
b101010100000 ,
b100010000000 -
b1100110000000 .
b0 /
b1001100100000 0
b1000100000000 1
b100010000000 2
b1101110100000 4
b0 5
b0 7
b0 9
b11001100000 :
b110011000000 ;
b1100110000000 <
b0 =

#335000
b10111010 !
b1011110 "
b111100111111010 #
b1011111001000110 $
b111011 %
b10111010 &
b1011110 '
b111100111111010 (
b100010001001100 )
b1110011100 *
b11000000 +
b111001110000 ,
b1100000000 -
b10111010000000 .
b10001101101100 0
b1110100100000 1
b1111000000 2
b10000010101100 4
b11010000000 5
b101110100 7
b1011101000 8
b10111010000 9
b101110100000 :
b0 ;
b10111010000000 <

#340000
b11010101 !
b11010 "
b10111001 #
b1011001011011 $
b111100 %
b11010101 &
b11010 '
b10111001 (
b1010110100010 )
b110101010 *
b0 +
b101111111000 ,
b100000000000 -
b0 .
b101001010010 0
b1101010000 1
b100000000000 2
b1001010010 4
b1000000000000 5
b110101010 7
b0 8
b11010101000 9
b110101010000 :
b0 <

#345000
b110111 !
b10010110 "
b10000111000000 #
b100000111111010 $
b111101 %
b110111 &
b10010110 '
b10000111000000 (
b10000000111010 )
b10110010 *
b10011000 +
b1101110000 ,
b0 -
b1101110000000 .
b1100001000010 0
b11101100000 1
b10011000 2
b1100011011010 4
b0 5
b1101110 7
b11011100 8
b0 9
b1101110000 :
b1101110000000 =

