src/csa3_16.v
module csa3_16(
  input  [15:0] x,
  input  [15:0] y,
  input  [15:0] z,
  output [15:0] sum,
  output [15:0] carry_sh
);
  assign sum = x ^ y ^ z;
  assign carry_sh = ((x & y) | (y & z) | (x & z)) << 1;
endmodule

src/multiplier_wallace.v
// 8x8 Wallace-like multiplier using carry-save adder (CSA) tree
module multiplier_wallace(
    input  [7:0] a,
    input  [7:0] b,
    output [15:0] product
);

  // 16-bit shifted partial products
  wire [15:0] pp_shift [7:0];
  genvar k;
  generate
    for (k = 0; k < 8; k = k + 1) begin : gen_pp_shifts
      // extend a into 16 bits then shift by k
      assign pp_shift[k] = b[k] ? ({8'b0, a} << k) : 16'b0;
    end
  endgenerate

  // Stage 1: reduce groups of three partial products
  wire [15:0] s1, c1, s2, c2, s3, c3;
  csa3_16 u1 (pp_shift[0], pp_shift[1], pp_shift[2], s1, c1);
  csa3_16 u2 (pp_shift[3], pp_shift[4], pp_shift[5], s2, c2);
  csa3_16 u3 (pp_shift[6], pp_shift[7], 16'b0,          s3, c3);

  // Stage 2: reduce the stage-1 sums and the stage-1 carries
  wire [15:0] s4, c4, s5, c5;
  csa3_16 u4 (s1, s2, s3, s4, c4);
  csa3_16 u5 (c1, c2, c3, s5, c5); // c1/c2/c3 already include their left-shift

  // Stage 3: reduce the two resulting sums
  wire [15:0] s6, c6;
  csa3_16 u6 (s4, s5, 16'b0, s6, c6);

  // Final: add remaining operands (s6 + c4 + c5 + c6). All carries produced by CSA are left-shifted.
  assign product = s6 + c4 + c5 + c6;

endmodule

// 3:2 carry-save adder for 16-bit vectors.
// sum = x ^ y ^ z
// carry_sh = ((x&y) | (y&z) | (x&z)) << 1  (carry bits shifted to next weight)

tb/tb_multiplier_wallace.v
`timescale 1ns/1ps

module tb_multiplier_wallace;

    reg  [7:0] a, b;
    wire [15:0] product;

    // Instantiate DUT
    multiplier_wallace uut (
        .a(a),
        .b(b),
        .product(product)
    );

    integer i;

    initial begin
        $dumpfile("waves/multiplier_wallace.vcd");
        $dumpvars(0, tb_multiplier_wallace);

        // Test vectors
        a = 8'd0;   b = 8'd0;   #10;
        a = 8'd5;   b = 8'd7;   #10;
        a = 8'd10;  b = 8'd14;  #10;
        a = 8'd25;  b = 8'd3;   #10;
        a = 8'd55;  b = 8'd22;  #10;
        a = 8'd100; b = 8'd12;  #10;
        a = 8'd255; b = 8'd1;   #10;
        a = 8'd255; b = 8'd255; #10;

         // Random exhaustive-ish tests (not full 65536 but many)
        for (i = 0; i < 2000; i = i + 1) begin
            a = $random % 256;
            b = $random % 256;
            #1;
            if (product !== ((a+0)*(b+0))) begin
                $display("ERROR: a=%0d b=%0d product=%0d expected=%0d", a, b, product, ((a+0)*(b+0)));
                $finish;
            end
            #4;
        end

        $display("All random checks passed.");
        $finish;
    end

endmodule

WT/WT.sim/sim_1/behav/xsim/dump.vcd
$date
   Mon Nov 17 11:20:06 2025
$end

$version
  2024.2.0
$end

$timescale
  1ps
$end

$scope module tb_multiplier_wallace $end
$var reg 8 ! a [7:0] $end
$var reg 8 " b [7:0] $end
$var wire 16 # product [15:0] $end
$var integer 32 $ i [31:0] $end
$scope module uut $end
$var wire 8 % a [7:0] $end
$var wire 8 & b [7:0] $end
$var wire 16 # product [15:0] $end
$var wire 16 ' s1 [15:0] $end
$var wire 16 ( c1 [15:0] $end
$var wire 16 ) s2 [15:0] $end
$var wire 16 * c2 [15:0] $end
$var wire 16 + s3 [15:0] $end
$var wire 16 , c3 [15:0] $end
$var wire 16 - s4 [15:0] $end
$var wire 16 . c4 [15:0] $end
$var wire 16 / s5 [15:0] $end
$var wire 16 0 c5 [15:0] $end
$var wire 16 1 s6 [15:0] $end
$var wire 16 2 c6 [15:0] $end
$scope module u1 $end
$var wire 16 3 x [15:0] $end
$var wire 16 4 y [31:16] $end
$var wire 16 5 z [47:32] $end
$var wire 16 ' sum [15:0] $end
$var wire 16 ( carry_sh [15:0] $end
$upscope $end
$scope module u2 $end
$var wire 16 6 x [63:48] $end
$var wire 16 7 y [79:64] $end
$var wire 16 8 z [95:80] $end
$var wire 16 ) sum [15:0] $end
$var wire 16 * carry_sh [15:0] $end
$upscope $end
$scope module u3 $end
$var wire 16 9 x [111:96] $end
$var wire 16 : y [127:112] $end
$var wire 16 ; z [15:0] $end
$var wire 16 + sum [15:0] $end
$var wire 16 , carry_sh [15:0] $end
$upscope $end
$scope module u4 $end
$var wire 16 ' x [15:0] $end
$var wire 16 ) y [15:0] $end
$var wire 16 + z [15:0] $end
$var wire 16 - sum [15:0] $end
$var wire 16 . carry_sh [15:0] $end
$upscope $end
$scope module u5 $end
$var wire 16 ( x [15:0] $end
$var wire 16 * y [15:0] $end
$var wire 16 , z [15:0] $end
$var wire 16 / sum [15:0] $end
$var wire 16 0 carry_sh [15:0] $end
$upscope $end
$scope module u6 $end
$var wire 16 - x [15:0] $end
$var wire 16 / y [15:0] $end
$var wire 16 < z [15:0] $end
$var wire 16 1 sum [15:0] $end
$var wire 16 2 carry_sh [15:0] $end
$upscope $end
$upscope $end
$upscope $end
$enddefinitions $end

#0
$dumpvars
b0 !
b0 "
b0 #
bx $
b0 %
b0 &
b0 '
b0 (
b0 )
b0 *
b0 +
b0 ,
b0 -
b0 .
b0 /
b0 0
b0 1
b0 2
b0 3
b0 4
b0 5
b0 6
b0 7
b0 8
b0 9
b0 :
b0 ;
b0 <
$end

#10000
b101 !
b111 "
b100011 #
b101 %
b111 &
b11011 '
b1000 (
b11011 -
b1000 /
b10011 1
b10000 2
b101 3
b1010 4
b10100 5

#20000
b1010 !
b1110 "
b10001100 #
b1010 %
b1110 &
b111100 '
b0 (
b1010000 )
b1101100 -
b100000 .
b0 /
b1101100 1
b0 2
b0 3
b10100 4
b101000 5
b1010000 6

#30000
b11001 !
b11 "
b1001011 #
b11001 %
b11 &
b101011 '
b100000 (
b0 )
b101011 -
b0 .
b100000 /
b1011 1
b1000000 2
b11001 3
b110010 4
b0 5
b0 6

#40000
b110111 !
b10110 "
b10010111010 #
b110111 %
b10110 &
b10110010 '
b10011000 (
b1101110000 )
b1111000010 -
b1100000 .
b10011000 /
b1101011010 1
b100000000 2
b0 3
b1101110 4
b11011100 5
b1101110000 7

#50000
b1100100 !
b1100 "
b10010110000 #
b1100100 %
b1100 &
b110010000 '
b0 (
b1100100000 )
b1010110000 -
b1000000000 .
b0 /
b1010110000 1
b0 2
b0 4
b110010000 5
b1100100000 6
b0 7

#60000
b11111111 !
b1 "
b11111111 #
b11111111 %
b1 &
b11111111 '
b0 )
b11111111 -
b0 .
b11111111 1
b11111111 3
b0 5
b0 6

#70000
b11111111 "
b1111111000000001 #
b11111111 &
b1011111101 '
b1111111100 (
b1011111101000 )
b1111111100000 *
b100000001000000 +
b111111100000000 ,
b101010101010101 -
b10111010000 .
b110001100011100 /
b11111111000000 0
b11011001001001 1
b1000001000101000 2
b111111110 4
b1111111100 5
b11111111000 6
b111111110000 7
b1111111100000 8
b11111111000000 9
b111111110000000 :

#80000
b100100 !
b10000001 "
b1001000100100 #
b0 $
b100100 %
b10000001 &
b100100 '
b0 (
b0 )
b0 *
b1001000000000 +
b0 ,
b1001000100100 -
b0 .
b0 /
b0 0
b1001000100100 1
b0 2
b100100 3
b0 4
b0 5
b0 6
b0 7
b0 8
b0 9
b1001000000000 :

#85000
b1001 !
b1100011 "
b1101111011 #
b1 $
b1001 %
b1100011 &
b11011 '
b100100000 )
b1001000000 +
b1101111011 -
b1101111011 1
b1001 3
b10010 4
b100100000 8
b1001000000 9
b0 :

#90000
b1101 !
b10001101 "
b11100101001 #
b10 $
b1101 %
b10001101 &
b111001 '
b1000 (
b1101000 )
b11010000000 +
b11011010001 -
b1010000 .
b1000 /
b11011011001 1
b1101 3
b0 4
b110100 5
b1101000 6
b0 8
b0 9
b11010000000 :

#95000
b1100101 !
b10010 "
b11100011010 #
b11 $
b1100101 %
b10010 &
b11001010 '
b0 (
b11001010000 )
b0 +
b11010011010 -
b10000000 .
b0 /
b11010011010 1
b0 3
b11001010 4
b0 5
b0 6
b11001010000 7
b0 :

#100000
b1 !
b1101 "
b1101 #
b100 $
b1 %
b1101 &
b101 '
b1000 )
b1101 -
b0 .
b1101 1
b1 3
b0 4
b100 5
b1000 6
b0 7

#105000
b1110110 !
b111101 "
b1110000011110 #
b101 $
b1110110 %
b111101 &
b110101110 '
b10100000 (
b101000010000 )
b111111000000 *
b101110111110 -
b111101100000 /
b100000000 0
b10011011110 1
b1011001000000 2
b1110110 3
b111011000 5
b1110110000 6
b11101100000 7
b111011000000 8

#110000
b11101101 !
b10001100 "
b1000000110011100 #
b110 $
b11101101 %
b10001100 &
b1110110100 '
b0 (
b11101101000 )
b0 *
b111011010000000 +
b111001001011100 -
b111101000000 .
b0 /
b0 0
b111001001011100 1
b0 2
b0 3
b1110110100 5
b11101101000 6
b0 7
b0 8
b111011010000000 :

#115000
b11111001 !
b11000110 "
b1100000010010110 #
b111 $
b11111001 %
b11000110 &
b1000010110 '
b1111000000 (
b0 )
b100001011000000 +
b111100000000000 ,
b100000011010110 -
b10000000000 .
b111101111000000 /
b11101100010110 1
b1000000110000000 2
b111110010 4
b1111100100 5
b0 6
b11111001000000 9
b111110010000000 :

#120000
b11000101 !
b10101010 "
b1000001011010010 #
b1000 $
b11000101 %
b10101010 &
b110001010 '
b0 (
b1111010001000 )
b1000000 *
b110001010000000 +
b0 ,
b111110110000010 -
b10100010000 .
b1000000 /
b111110111000010 1
b0 2
b110001010 4
b0 5
b11000101000 6
b1100010100000 8
b0 9
b110001010000000 :

#125000
b11100101 !
b1110111 "
b110101001110011 #
b1001 $
b11100101 %
b1110111 &
b1010111011 '
b1110001000 (
b1001011110000 )
b1100000000000 *
b11100101000000 +
b10100100001011 -
b10010111100000 .
b1101110001000 /
b11001010000011 1
b1001000010000 2
b11100101 3
b111001010 4
b1110010100 5
b0 6
b111001010000 7
b1110010100000 8
b11100101000000 9
b0 :

#130000
b10010 !
b10001111 "
b101000001110 #
b1010 $
b10010 %
b10001111 &
b1111110 '
b0 (
b10010000 )
b0 *
b100100000000 +
b100111101110 -
b100000 .
b0 /
b100111101110 1
b0 2
b10010 3
b100100 4
b1001000 5
b10010000 6
b0 7
b0 8
b0 9
b100100000000 :

#135000
b11110010 !
b11001110 "
b1100001010111100 #
b1011 $
b11110010 %
b11001110 &
b1000101100 '
b1110000000 (
b11110010000 )
b100010110000000 +
b111000000000000 ,
b100000000111100 -
b111100000000 .
b111001110000000 /
b11001110111100 1
b1000000000000000 2
b0 3
b111100100 4
b1111001000 5
b11110010000 6
b11110010000000 9
b111100100000000 :

#140000
b11101000 !
b11000101 "
b1011001010001000 #
b1100 $
b11101000 %
b11000101 &
b1101001000 '
b101000000 (
b0 )
b100111000000000 +
b110000000000000 ,
b100110101001000 -
b10000000000 .
b110000101000000 /
b10110000001000 1
b1000001010000000 2
b11101000 3
b0 4
b1110100000 5
b0 6
b11101000000000 9
b111010000000000 :

#145000
b1011100 !
b10111101 "
b100001111101100 #
b1101 $
b1011100 %
b10111101 &
b100101100 '
b10100000 (
b110010100000 )
b11110000000 *
b10111000000000 +
b0 ,
b10001110001100 -
b1100001000000 .
b11100100000 /
b100000000 0
b10010010101100 1
b11000000000 2
b1011100 3
b101110000 5
b1011100000 6
b10111000000 7
b101110000000 8
b0 9
b10111000000000 :

#150000
b101101 !
b1100101 "
b1000111000001 #
b1110 $
b101101 %
b1100101 &
b10011001 '
b1001000 (
b10110100000 )
b0 *
b101101000000 +
b111001111001 -
b1100000000 .
b1001000 /
b0 0
b111000110001 1
b10010000 2
b101101 3
b10110100 5
b0 6
b0 7
b10110100000 8
b101101000000 9
b0 :

#155000
b1100011 !
b1010 "
b1111011110 #
b1111 $
b1100011 %
b1010 &
b11000110 '
b0 (
b1100011000 )
b0 +
b1111011110 -
b0 .
b0 /
b1111011110 1
b0 2
b0 3
b11000110 4
b0 5
b1100011000 6
b0 8
b0 9

#160000
b10000000 !
b100000 "
b1000000000000 #
b10000 $
b10000000 %
b100000 &
b0 '
b1000000000000 )
b1000000000000 -
b1000000000000 1
b0 4
b0 6
b1000000000000 8

#165000
b10101010 !
b10011101 "
b110100001000010 #
b10001 $
b10101010 %
b10011101 &
b1000000010 '
b101010000 (
b111111110000 )
b101010100000000 +
b101100011110010 -
b111000000000 .
b101010000 /
b101100110100010 1
b10100000 2
b10101010 3
b1010101000 5
b10101010000 6
b101010100000 7
b0 8
b101010100000000 :

#170000
b10010110 !
b10011 "
b101100100010 #
b10010 $
b10010110 %
b10011 &
b110111010 '
b1000 (
b100101100000 )
b0 +
b100011011010 -
b1001000000 .
b1000 /
b100011010010 1
b10000 2
b10010110 3
b100101100 4
b0 5
b0 6
b100101100000 7
b0 :

#175000
b1101 !
b1010011 "
b10000110111 #
b10011 $
b1101 %
b1010011 &
b10111 '
b10000 (
b11010000 )
b1101000000 +
b1110000111 -
b10100000 .
b10000 /
b1110010111 1
b0 2
b1101 3
b11010 4
b11010000 7
b1101000000 9

#180000
b1101011 !
b11010101 "
b101100100000111 #
b10100 $
b1101011 %
b11010101 &
b111000111 '
b1010000 (
b11010110000 )
b10111101000000 +
b10000100000000 ,
b10100000110111 -
b111110000000 .
b10000101010000 /
b100101100111 1
b100000000100000 2
b1101011 3
b0 4
b110101100 5
b11010110000 7
b1101011000000 9
b11010110000000 :

#185000
b10 !
b10101110 "
b101011100 #
b10101 $
b10 %
b10101110 &
b1100 '
b0 (
b1010000 )
b100000000 +
b0 ,
b101011100 -
b0 .
b0 /
b101011100 1
b0 2
b0 3
b100 4
b1000 5
b10000 6
b0 7
b1000000 8
b0 9
b100000000 :

#190000
b11101 !
b11001111 "
b1011101110011 #
b10110 $
b11101 %
b11001111 &
b1010011 '
b1111000 (
b11101000 )
b100111000000 +
b110000000000 ,
b100101111011 -
b110000000 .
b110001111000 /
b10100000011 1
b1000011110000 2
b11101 3
b111010 4
b1110100 5
b11101000 6
b0 8
b11101000000 9
b111010000000 :

#195000
b100011 !
b1010 "
b101011110 #
b10111 $
b100011 %
b1010 &
b1000110 '
b0 (
b100011000 )
b0 +
b0 ,
b101011110 -
b0 .
b0 /
b101011110 1
b0 2
b0 3
b1000110 4
b0 5
b100011000 6
b0 9
b0 :

#200000
b11001010 !
b111100 "
b10111101011000 #
b11000 $
b11001010 %
b111100 &
b1100101000 '
b1001110110000 )
b1100010000000 *
b1000010011000 -
b11001000000 .
b1100010000000 /
b100000011000 1
b10000100000000 2
b0 4
b1100101000 5
b11001010000 6
b110010100000 7
b1100101000000 8

#205000
b11110010 !
b10001010 "
b1000001001110100 #
b11001 $
b11110010 %
b10001010 &
b111100100 '
b11110010000 )
b0 *
b111100100000000 +
b111111101110100 -
b1100000000 .
b0 /
b111111101110100 1
b0 2
b111100100 4
b0 5
b11110010000 6
b0 7
b0 8
b111100100000000 :

#210000
b1000001 !
b11011000 "
b11011011011000 #
b11010 $
b1000001 %
b11011000 &
b0 '
b11000011000 )
b11000011000000 +
b11011011011000 -
b0 .
b11011011011000 1
b0 4
b1000001000 6
b10000010000 7
b1000001000000 9
b10000010000000 :

#215000
b1111000 !
b10001001 "
b100000000111000 #
b11011 $
b1111000 %
b10001001 &
b1111000 '
b1111000000 )
b11110000000000 +
b11111110111000 -
b10000000 .
b11111110111000 1
b1111000 3
b1111000000 6
b0 7
b0 9
b11110000000000 :

#220000
b11101011 !
b10110110 "
b1010011100010010 #
b11100 $
b11101011 %
b10110110 &
b1001111010 '
b1100001000 (
b1001111010000 )
b1100001000000 *
b111010110000000 +
b110010000101010 -
b10011110100000 .
b1101101001000 /
b111111101100010 1
b10000 2
b0 3
b111010110 4
b1110101100 5
b0 6
b111010110000 7
b1110101100000 8
b111010110000000 :

#225000
b11000110 !
b10101110 "
b1000011010010100 #
b11101 $
b11000110 %
b10101110 &
b1010010100 '
b1000010000 (
b1111011110000 )
b0 *
b110001100000000 +
b111111101100100 -
b10100100000 .
b1000010000 /
b111110101110100 1
b10000000000 2
b110001100 4
b1100011000 5
b11000110000 6
b0 7
b1100011000000 8
b110001100000000 :

#230000
b10111100 !
b101010 "
b1111011011000 #
b11110 $
b10111100 %
b101010 &
b101111000 '
b0 (
b1001001100000 )
b101100000000 *
b0 +
b1001100011000 -
b11000000 .
b101100000000 /
b1100000011000 1
b11000000000 2
b101111000 4
b0 5
b10111100000 6
b1011110000000 8
b0 :

#235000
b1011 !
b1110001 "
b10011011011 #
b11111 $
b1011 %
b1110001 &
b1011 '
b111010000 )
b1000000 *
b1011000000 +
b1100011011 -
b110000000 .
b1000000 /
b1101011011 1
b0 2
b1011 3
b0 4
b0 6
b10110000 7
b101100000 8
b1011000000 9

#240000
b10000101 !
b1001111 "
b10100100001011 #
b100000 $
b10000101 %
b1001111 &
b1110011011 '
b1000 (
b10000101000 )
b0 *
b10000101000000 +
b10011011110011 -
b1000010000 .
b1000 /
b10011011111011 1
b10000101 3
b100001010 4
b1000010100 5
b10000101000 6
b0 7
b0 8
b10000101000000 9

#245000
b111011 !
b111010 "
b110101011110 #
b100001 $
b111011 %
b111010 &
b1110110 '
b0 (
b10100001000 )
b11111100000 *
b0 +
b10101111110 -
b0 .
b11111100000 /
b1010011110 1
b101011000000 2
b0 3
b1110110 4
b0 5
b111011000 6
b1110110000 7
b11101100000 8
b0 9

#250000
b1111110 !
b10101 "
b101001010110 #
b100010 $
b1111110 %
b10101 &
b110000110 '
b11110000 (
b11111100000 )
b0 *
b11001100110 -
b1100000000 .
b11110000 /
b11010010110 1
b11000000 2
b1111110 3
b0 4
b111111000 5
b0 6
b11111100000 7
b0 8

#255000
b11110001 !
b11011001 "
b1100110001001001 #
b100011 $
b11110001 %
b11011001 &
b11110001 '
b0 (
b100010011000 )
b111000000000 *
b100010011000000 +
b111000000000000 ,
b100110010101001 -
b110100000 .
b111111000000000 /
b11001010101001 1
b1001100000000000 2
b11110001 3
b0 5
b11110001000 6
b111100010000 7
b11110001000000 9
b111100010000000 :

#260000
b1100010 !
b1001100 "
b1110100011000 #
b100100 $
b1100010 %
b1001100 &
b110001000 '
b1100010000 )
b0 *
b1100010000000 +
b0 ,
b1101000011000 -
b1100000000 .
b0 /
b1101000011000 1
b0 2
b0 3
b110001000 5
b1100010000 6
b0 7
b1100010000000 9
b0 :

#265000
b10011111 !
b10001111 "
b101100011010001 #
b100101 $
b10011111 %
b10001111 &
b1111011101 '
b1111100 (
b10011111000 )
b100111110000000 +
b100100010100101 -
b111110110000 .
b1111100 /
b100100011011001 1
b1001000 2
b10011111 3
b100111110 4
b1001111100 5
b10011111000 6
b0 9
b100111110000000 :

#270000
b11111000 !
b10110111 "
b1011000101001000 #
b100110 $
b11111000 %
b10110111 &
b1011101000 '
b1111100000 (
b1000010000000 )
b1111000000000 *
b111110000000000 +
b110111001101000 -
b10000100000000 .
b1110111100000 /
b10000000000 0
b111001110001000 1
b1100011000000 2
b11111000 3
b111110000 4
b1111100000 5
b0 6
b111110000000 7
b1111100000000 8
b111110000000000 :

#275000
b10011111 !
b1011100 "
b11100100100100 #
b100111 $
b10011111 %
b1011100 &
b1001111100 '
b0 (
b110100001000 )
b111100000 *
b10011111000000 +
b10100010110100 -
b111010010000 .
b111100000 /
b0 0
b10100101010100 1
b101000000 2
b0 3
b0 4
b1001111100 5
b10011111000 6
b100111110000 7
b0 8
b10011111000000 9
b0 :

#280000
b1011011 !
b10001001 "
b11000010110011 #
b101000 $
b1011011 %
b10001001 &
b1011011 '
b1011011000 )
b0 *
b10110110000000 +
b10111100000011 -
b110110000 .
b0 /
b10111100000011 1
b0 2
b1011011 3
b0 5
b1011011000 6
b0 7
b0 9
b10110110000000 :

#285000
b1001001 !
b11010000 "
b11101101010000 #
b101001 $
b1001001 %
b11010000 &
b0 '
b10010010000 )
b11011011000000 +
b11001001010000 -
b100100000000 .
b11001001010000 1
b0 3
b0 6
b10010010000 7
b1001001000000 9
b10010010000000 :

#290000
b11010111 !
b1010001 "
b100010000000111 #
b101010 $
b11010111 %
b1010001 &
b11010111 '
b110101110000 )
b11010111000000 +
b11100001100111 -
b101110100000 .
b11100001100111 1
b11010111 3
b110101110000 7
b11010111000000 9
b0 :

#295000
b10010110 !
b1100 "
b11100001000 #
b101011 $
b10010110 %
b1100 &
b1001011000 '
b10010110000 )
b0 +
b11011101000 -
b100000 .
b11011101000 1
b0 3
b1001011000 5
b10010110000 6
b0 7
b0 9

#300000
b11000010 !
b11001000 "
b1001011110010000 #
b101100 $
b11000010 %
b11001000 &
b0 '
b11000010000 )
b101000110000000 +
b100000000000000 ,
b101011110010000 -
b0 .
b100000000000000 /
b1011110010000 1
b1000000000000000 2
b0 5
b11000010000 6
b11000010000000 9
b110000100000000 :

#305000
b1110111 !
b111101 "
b1110001011011 #
b101101 $
b1110111 %
b111101 &
b110101011 '
b10101000 (
b101000101000 )
b111111100000 *
b0 +
b0 ,
b101110000011 -
b1010000 .
b111101001000 /
b101000000 0
b10011001011 1
b1011000000000 2
b1110111 3
b111011100 5
b1110111000 6
b11101110000 7
b111011100000 8
b0 9
b0 :

#310000
b10010 !
b1111110 "
b100011011100 #
b101110 $
b10010 %
b1111110 &
b1101100 '
b0 (
b1111110000 )
b0 *
b10010000000 +
b11100011100 -
b111000000 .
b0 /
b0 0
b11100011100 1
b0 2
b0 3
b100100 4
b1001000 5
b10010000 6
b100100000 7
b1001000000 8
b10010000000 9

#315000
b1101101 !
b111001 "
b1100001000101 #
b101111 $
b1101101 %
b111001 &
b1101101 '
b100000011000 )
b111111000000 *
b0 +
b100001110101 -
b10000 .
b111111000000 /
b11110110101 1
b1000010000000 2
b1101101 3
b0 4
b0 5
b1101101000 6
b11011010000 7
b110110100000 8
b0 9

#320000
b11111 !
b11010011 "
b1100110001101 #
b110000 $
b11111 %
b11010011 &
b100001 '
b111100 (
b111110000 )
b0 *
b100001000000 +
b111100000000 ,
b100110010001 -
b11000000 .
b111100111100 /
b11010101101 1
b1001000100000 2
b11111 3
b111110 4
b0 6
b111110000 7
b0 8
b11111000000 9
b111110000000 :

#325000
b10000101 !
b1111000 "
b11111001011000 #
b110001 $
b10000101 %
b1111000 &
b0 '
b0 (
b1110011011000 )
b1000000 *
b10000101000000 +
b0 ,
b11110110011000 -
b10000000 .
b1000000 /
b11110111011000 1
b0 2
b0 3
b0 4
b10000101000 6
b100001010000 7
b1000010100000 8
b10000101000000 9
b0 :

#330000
b1011011 !
b1001001 "
b1100111110011 #
b110010 $
b1011011 %
b1001001 &
b1011011 '
b1011011000 )
b0 *
b1011011000000 +
b1010001000011 -
b10110110000 .
b0 /
b1010001000011 1
b1011011 3
b1011011000 6
b0 7
b0 8
b1011011000000 9

#335000
b111111 !
b101010 "
b101001010110 #
b110011 $
b111111 %
b101010 &
b1111110 '
b11000011000 )
b1111000000 *
b0 +
b11001100110 -
b110000 .
b1111000000 /
b10110100110 1
b10010000000 2
b0 3
b1111110 4
b111111000 6
b11111100000 8
b0 9

#340000
b1011000 !
b10000110 "
b10111000010000 #
b110100 $
b1011000 %
b10000110 &
b111010000 '
b1000000 (
b0 )
b0 *
b10110000000000 +
b10110111010000 -
b0 .
b1000000 /
b10110110010000 1
b10000000 2
b10110000 4
b101100000 5
b0 6
b0 8
b10110000000000 :

#345000
b10001110 !
b10011100 "
b101011010001000 #
b110101 $
b10001110 %
b10011100 &
b1000111000 '
b0 (
b110010010000 )
b11000000 *
b100011100000000 +
b100100110101000 -
b110000100000 .
b11000000 /
b100100101101000 1
b100000000 2
b0 4
b1000111000 5
b10001110000 6
b100011100000 7
b100011100000000 :

#350000
b11111010 !
b100110 "
b10010100011100 #
b110110 $
b11111010 %
b100110 &
b1000011100 '
b1111000000 (
b1111101000000 )
b0 *
b0 +
b1110101011100 -
b10000000000 .
b1111000000 /
b1111010011100 1
b1010000000 2
b111110100 4
b1111101000 5
b0 6
b0 7
b1111101000000 8
b0 :

#355000
b1110011 !
b10100011 "
b100100100111001 #
b110111 $
b1110011 %
b10100011 &
b10010101 '
b11000100 (
b111001100000 )
b11100110000000 +
b11011101110101 -
b1000100000000 .
b11000100 /
b11011110110001 1
b10001000 2
b1110011 3
b11100110 4
b0 5
b111001100000 8
b11100110000000 :

#360000
b101111 !
b10110011 "
b10000011011101 #
b111000 $
b101111 %
b10110011 &
b1110001 '
b11100 (
b11100010000 )
b111000000 *
b1011110000000 +
b1000011100001 -
b111000100000 .
b111011100 /
b1000100111101 1
b110000000 2
b101111 3
b1011110 4
b1011110000 7
b10111100000 8
b1011110000000 :

#365000
b1011111 !
b1000100 "
b1100100111100 #
b111001 $
b1011111 %
b1000100 &
b101111100 '
b0 (
b0 )
b0 *
b1011111000000 +
b1011010111100 -
b1010000000 .
b0 /
b1011010111100 1
b0 2
b0 3
b0 4
b101111100 5
b0 7
b0 8
b1011111000000 9
b0 :

#370000
b11110111 !
b11001011 "
b1100001111011101 #
b111010 $
b11110111 %
b11001011 &
b100011001 '
b111001100 (
b11110111000 )
b100011001000000 +
b111001100000000 ,
b100000011100001 -
b111000110000 .
b111001011001100 /
b1000000000 0
b11001000101101 1
b1000000110000000 2
b11110111 3
b111101110 4
b0 5
b11110111000 6
b11110111000000 9
b111101110000000 :

#375000
b11100110 !
b1011010 "
b101000011011100 #
b111011 $
b11100110 %
b1011010 &
b111001100 '
b0 (
b100101010000 )
b110001000000 *
b11100110000000 +
b0 ,
b11000100011100 -
b1001110000000 .
b110001000000 /
b0 0
b11110101011100 1
b0 2
b0 3
b111001100 4
b11100110000 6
b111001100000 7
b11100110000000 9
b0 :

#380000
b101001 !
b11101101 "
b10010111110101 #
b111100 $
b101001 %
b11101101 &
b10001101 '
b1000000 (
b10001101000 )
b1000000000 *
b1111011000000 +
b1101000100101 -
b100110010000 .
b1001000000 /
b1100001100101 1
b10000000000 2
b101001 3
b0 4
b10100100 5
b101001000 6
b0 7
b10100100000 8
b101001000000 9
b1010010000000 :

#385000
b11011010 !
b1100101 "
b101011000000010 #
b111101 $
b11011010 %
b1100101 &
b1110110010 '
b10010000 (
b1101101000000 )
b0 *
b11011010000000 +
b10111001110010 -
b10011100000000 .
b10010000 /
b10111011100010 1
b100000 2
b11011010 3
b1101101000 5
b0 6
b1101101000000 8
b11011010000000 9
b0 :

#390000
b10110101 !
b11011111 "
b1001110110101011 #
b111110 $
b10110101 %
b11011111 &
b1100001011 '
b111101000 (
b111011111000 )
b1000000000 *
b111011111000000 +
b1000000000000 ,
b111101000110011 -
b111110010000 .
b1001111101000 /
b110100111011011 1
b10010001000000 2
b10110101 3
b101101010 4
b1011010100 5
b10110101000 6
b101101010000 7
b0 8
b10110101000000 9
b101101010000000 :

#395000
b1111001 !
b1000100 "
b10000000100100 #
b111111 $
b1111001 %
b1000100 &
b111100100 '
b0 (
b0 )
b0 *
b1111001000000 +
b0 ,
b1111110100100 -
b10000000 .
b0 /
b1111110100100 1
b0 2
b0 3
b0 4
b111100100 5
b0 6
b0 7
b1111001000000 9
b0 :

#400000
b11010000 !
b101010 "
b10001000100000 #
b1000000 $
b11010000 %
b101010 &
b110100000 '
b1110010000000 )
b10000000000 *
b0 +
b1110100100000 -
b100000000 .
b10000000000 /
b1100100100000 1
b100000000000 2
b110100000 4
b0 5
b11010000000 6
b1101000000000 8
b0 9

#405000
b10101011 !
b1110 "
b100101011010 #
b1000001 $
b10101011 %
b1110 &
b1111111010 '
b1000 (
b10101011000 )
b0 *
b11010100010 -
b1010110000 .
b1000 /
b11010101010 1
b0 2
b101010110 4
b1010101100 5
b10101011000 6
b0 8

#410000
b11011100 !
b10011010 "
b1000010001011000 #
b1000010 $
b11011100 %
b10011010 &
b110111000 '
b0 (
b101100100000 )
b100110000000 *
b110111000000000 +
b110010010011000 -
b1011001000000 .
b100110000000 /
b110110100011000 1
b100000000 2
b110111000 4
b0 5
b11011100000 6
b110111000000 7
b110111000000000 :

#415000
b11111101 !
b11000011 "
b1100000010110111 #
b1000011 $
b11111101 %
b11000011 &
b100000111 '
b111110000 (
b0 )
b0 *
b100000111000000 +
b111110000000000 ,
b100000011000111 -
b1000000000 .
b111110111110000 /
b11110100110111 1
b1000000110000000 2
b11111101 3
b111111010 4
b0 6
b0 7
b11111101000000 9
b111111010000000 :

#420000
b1010110 !
b1001110 "
b1101000110100 #
b1000100 $
b1010110 %
b1001110 &
b111110100 '
b10000 (
b1010110000 )
b1010110000000 +
b0 ,
b1011011000100 -
b1101100000 .
b10000 /
b1011011010100 1
b0 2
b0 3
b10101100 4
b101011000 5
b1010110000 6
b1010110000000 9
b0 :

#425000
b1100111 !
b1010 "
b10000000110 #
b1000101 $
b1100111 %
b1010 &
b11001110 '
b0 (
b1100111000 )
b0 +
b1111110110 -
b10000 .
b0 /
b1111110110 1
b11001110 4
b0 5
b1100111000 6
b0 9

#430000
b10110110 !
b111000 "
b10011111010000 #
b1000110 $
b10110110 %
b111000 &
b0 '
b1100000010000 )
b111111000000 *
b1100000010000 -
b0 .
b111111000000 /
b1011111010000 1
b1000000000000 2
b0 4
b10110110000 6
b101101100000 7
b1011011000000 8

#435000
b1111001 !
b10111000 "
b101011011111000 #
b1000111 $
b1111001 %
b10111000 &
b101101111000 )
b111100000000 *
b11110010000000 +
b11011111111000 -
b1000000000000 .
b111100000000 /
b11100011111000 1
b111000000000 2
b1111001000 6
b11110010000 7
b111100100000 8
b11110010000000 :

#440000
b10010100 !
b10010011 "
b101010011111100 #
b1001000 $
b10010100 %
b10010011 &
b110111100 '
b100101000000 )
b0 *
b100101000000000 +
b100001011111100 -
b1001000000000 .
b0 /
b100001011111100 1
b0 2
b10010100 3
b100101000 4
b0 6
b100101000000 7
b0 8
b100101000000000 :

